{"skeleton":{"hash":"nceWsa5RgvrYjGVBZY21X3iARKY","spine":"3.8.99","x":-229.64,"y":-5.77,"width":510,"height":434,"images":"./images/","audio":"C:/Users/user/Desktop/animation/안경고양이"},"bones":[{"name":"root","x":1.72},{"name":"Center","parent":"root","x":-38.31,"y":33.74},{"name":"body_01","parent":"Center","length":92.04,"rotation":88.49,"x":5.14,"y":31.97},{"name":"body_02","parent":"body_01","length":104.22,"rotation":3.91,"x":86.81},{"name":"nack","parent":"body_02","length":32.06,"rotation":-2.4,"x":81.74,"y":0.57},{"name":"head","parent":"nack","length":118.35,"rotation":-1.17,"x":23.98},{"name":"ear_R","parent":"head","length":64.82,"rotation":-4.37,"x":103.6,"y":-59.56},{"name":"ear_L","parent":"head","length":62.26,"rotation":27.82,"x":104.44,"y":33},{"name":"hair_03","parent":"head","length":35.35,"rotation":117.73,"x":126.78,"y":2.84},{"name":"hair_02","parent":"head","length":22.8,"rotation":-181.69,"x":127.82,"y":-5.82},{"name":"hair_01","parent":"head","length":22.22,"rotation":-129.32,"x":129.64,"y":-10.12},{"name":"hair_05","parent":"head","length":15.74,"rotation":-42.71,"x":124.62,"y":-18.89},{"name":"hair_04","parent":"head","length":16.76,"rotation":31.87,"x":127.73,"y":-1.48},{"name":"shoulder_L","parent":"body_02","length":72.24,"rotation":167.52,"x":63.89,"y":44.15},{"name":"shoulder_R","parent":"body_02","length":73.68,"rotation":-177.81,"x":68.64,"y":-63.75},{"name":"arm_R","parent":"shoulder_R","length":47.72,"rotation":-42.16,"x":70.77},{"name":"arm_L","parent":"shoulder_L","length":34.69,"rotation":25.91,"x":70.6},{"name":"hand_L","parent":"arm_L","rotation":74.17,"x":35.7,"y":4.36},{"name":"hand_L2","parent":"Center","x":-26.5,"y":81.87},{"name":"hand_R2","parent":"Center","x":21.9,"y":71.58},{"name":"book","parent":"root","rotation":0.01,"x":-91.79,"y":44.35},{"name":"box_01-L","parent":"book","rotation":-0.01,"x":-58.15,"y":63.03},{"name":"book_01","parent":"root","length":124.17,"rotation":73.04,"x":73.98,"y":54.95},{"name":"box_01-R","parent":"Center","x":121.46,"y":64.98},{"name":"box_02","parent":"box_01-R","rotation":2.7,"x":61.31,"y":5.96},{"name":"book_02","parent":"root","x":204.3,"y":40.72},{"name":"box_05","parent":"box_01-L","rotation":2.7,"x":18.47,"y":4.22},{"name":"galss","parent":"head","x":76.21,"y":8.41},{"name":"eye_light","parent":"head","x":79.11,"y":-30.44,"scaleX":0.9852,"scaleY":0.9852},{"name":"sparkle","parent":"head","rotation":88.83,"x":74.05,"y":51.37,"transform":"noRotationOrReflection"},{"name":"tail_01","parent":"body_01","length":53.22,"rotation":-23.13,"x":64.82,"y":-103.47},{"name":"tail_02","parent":"tail_01","length":73.05,"rotation":-32.16,"x":52.18,"y":-0.39},{"name":"tail_03","parent":"tail_02","x":110.7,"y":63.84},{"name":"hand_R","parent":"arm_R","rotation":127.57,"x":55.47,"y":-4.81},{"name":"book_05","parent":"book","x":7.43,"y":165.45},{"name":"eye_light2","parent":"head","x":69.44,"y":31.26,"scaleX":0.7309,"scaleY":0.7309},{"name":"book_04","parent":"book","x":-2.95,"y":104.93},{"name":"book_06","parent":"book","x":9.5,"y":201.65}],"slots":[{"name":"book_06","bone":"book_06","attachment":"book_06"},{"name":"book_05","bone":"book_05","attachment":"book_05"},{"name":"book_04","bone":"book_04","attachment":"book_04"},{"name":"book_03","bone":"book","attachment":"book_03"},{"name":"book_02","bone":"book_02","attachment":"book_02"},{"name":"box_05","bone":"box_05","attachment":"box_05"},{"name":"box_04","bone":"Center","attachment":"box_04"},{"name":"box_03","bone":"Center","attachment":"box_03"},{"name":"book_01","bone":"book_01","attachment":"book_01"},{"name":"tail","bone":"tail_01","attachment":"tail"},{"name":"body","bone":"body_01","attachment":"body"},{"name":"shoulder_L","bone":"shoulder_L","attachment":"shoulder_L"},{"name":"arm_L_03","bone":"shoulder_L","attachment":"arm_L_03"},{"name":"arm_L_01","bone":"arm_L","attachment":"arm_L_01"},{"name":"arm_L_02","bone":"shoulder_L","attachment":"arm_L_02"},{"name":"shoulder_R","bone":"shoulder_R","attachment":"shoulder_R"},{"name":"arm_R_03","bone":"shoulder_R","attachment":"arm_R_03"},{"name":"arm_R_01","bone":"arm_R","attachment":"arm_R_01"},{"name":"arm_R_02","bone":"shoulder_R","attachment":"arm_R_02"},{"name":"neck","bone":"nack","attachment":"neck"},{"name":"neck_02","bone":"nack","attachment":"neck_02"},{"name":"ear_L","bone":"ear_L","attachment":"ear_L"},{"name":"head","bone":"head","attachment":"head"},{"name":"eye_01","bone":"head","color":"ffffff00","attachment":"eye_01"},{"name":"eye_02","bone":"head","color":"ffffff00","attachment":"eye_02"},{"name":"ear_R","bone":"ear_R","attachment":"ear_R"},{"name":"ear_L-2","bone":"ear_L","color":"ffffff00","attachment":"ear_L-2"},{"name":"head2","bone":"head","color":"ffffff00","attachment":"head2"},{"name":"face_effect","bone":"head","color":"ffffff00","attachment":"face_effect","blend":"screen"},{"name":"eye_light","bone":"eye_light","color":"ffffff00","attachment":"eye_light"},{"name":"eye_light2","bone":"eye_light","color":"ffffff00","attachment":"eye_light"},{"name":"eye_light3","bone":"eye_light2","color":"ffffff00","attachment":"eye_light"},{"name":"eye_light4","bone":"eye_light2","color":"ffffff00","attachment":"eye_light"},{"name":"face_01","bone":"head","color":"ffffff00","attachment":"face_01"},{"name":"face-02","bone":"head","color":"ffffff00","attachment":"face-02"},{"name":"ear_R-2","bone":"ear_R","color":"ffffff00","attachment":"ear_R-2"},{"name":"eye2_01","bone":"head","color":"ffffff00","attachment":"eye2_01"},{"name":"eye2_02","bone":"head","color":"ffffff00","attachment":"eye2_02"},{"name":"head_shadow-2","bone":"galss","color":"ffffff00","attachment":"head_shadow-2"},{"name":"head_02-2","bone":"galss","color":"ffffff00","attachment":"head_02-2"},{"name":"hair_05","bone":"hair_05","attachment":"hair_05"},{"name":"hair_04","bone":"hair_04","attachment":"hair_04"},{"name":"hair_03","bone":"hair_03","attachment":"hair_03"},{"name":"hair_02","bone":"hair_02","attachment":"hair_02"},{"name":"hair_01","bone":"hair_01","attachment":"hair_01"},{"name":"head_03","bone":"galss","attachment":"head_03"},{"name":"head_02","bone":"galss","attachment":"head_02"},{"name":"box_01","bone":"Center","attachment":"box_01"},{"name":"box_02","bone":"box_02","attachment":"box_02"},{"name":"hand_L","bone":"hand_L","attachment":"hand_L"},{"name":"hand_R","bone":"hand_R","attachment":"hand_R"},{"name":"sparkle","bone":"sparkle","color":"ffffff00","attachment":"sparkle"}],"skins":[{"name":"default","attachments":{"arm_L_01":{"arm_L_01":{"x":18.83,"y":-4.12,"rotation":74.17,"width":45,"height":71}},"arm_L_02":{"arm_L_02":{"x":68.61,"y":-1.7,"rotation":100.08,"width":70,"height":66}},"arm_L_03":{"arm_L_03":{"x":96.47,"y":-1.32,"rotation":100.08,"width":69,"height":83}},"arm_R_01":{"arm_R_01":{"x":27.91,"y":-4.34,"rotation":127.57,"width":67,"height":73}},"arm_R_02":{"arm_R_02":{"x":87.32,"y":0.22,"rotation":85.41,"width":87,"height":115}},"arm_R_03":{"arm_R_03":{"x":97.76,"y":-7.14,"rotation":85.41,"width":74,"height":103}},"body":{"body":{"type":"mesh","uvs":[0.56514,0.08079,0.68856,0.13752,0.77314,0.27556,0.84527,0.40743,0.88472,0.52614,0.93322,0.61774,0.97931,0.65454,0.97931,0.78194,0.88792,0.87574,0.79146,0.95414,0.65946,1,0.38531,1,0.15008,0.93734,0.06377,0.86874,0,0.75814,0,0.66854,0,0.50614,0,0.29068,0,0.16588,0.09428,0.04865,0.20628,0,0.30914,0,0.41885,0,0.14685,0.32094,0.18571,0.18858,0.19256,0.09214,0.32742,0.09403,0.43485,0.08458,0.46823,0.18414,0.34469,0.18414,0.34977,0.32974,0.54269,0.32694,0.59854,0.50194,0.35823,0.51874,0.145,0.50894,0.14669,0.70634,0.38531,0.72174,0.64423,0.70634,0.39546,0.89394,0.16023,0.87434,0.651,0.88414,0.85407,0.79034],"triangles":[31,1,2,30,28,31,27,22,0,25,19,20,26,21,22,26,22,27,28,27,0,29,26,27,29,27,28,24,19,25,18,19,24,25,20,21,26,25,21,17,18,24,23,17,24,1,31,28,1,28,0,30,29,28,24,25,26,24,26,29,24,29,30,23,24,30,16,17,23,34,16,23,30,34,23,32,31,2,32,2,3,33,30,31,33,31,32,32,3,4,37,32,4,37,4,5,34,33,35,15,34,35,36,33,32,36,32,37,35,33,36,14,15,35,6,41,5,41,37,5,6,7,41,13,14,35,39,35,36,13,35,39,8,41,7,40,37,41,9,40,41,36,37,40,38,36,40,39,36,38,12,13,39,8,9,41,38,12,39,11,12,38,10,40,9,38,40,10,11,38,10,15,16,34,33,34,30],"vertices":[1,3,85.61,-58.02,1,2,2,164.29,-74.83,0.118,3,72.19,-79.94,0.882,2,2,134.33,-91.02,0.38073,3,41.21,-94.04,0.61927,2,2,105.68,-104.9,0.69067,3,11.67,-105.94,0.30933,2,2,79.76,-112.77,0.92289,3,-14.72,-112.02,0.07711,2,2,59.85,-122.12,0.99812,3,-35.23,-120,0.00188,2,2,51.97,-130.72,0.99988,3,-43.67,-128.04,1.2E-4,1,2,23.96,-131.46,1,1,2,2.89,-115.37,1,1,2,-14.82,-98.28,1,1,2,-25.53,-74.53,1,1,2,-26.85,-24.65,1,1,2,-14.19,18.51,1,1,2,0.48,34.61,1,1,2,24.5,46.85,1,1,2,44.21,47.37,1,2,2,79.92,48.31,0.51824,3,-3.58,48.67,0.48176,2,2,127.3,49.56,0.28378,3,43.78,46.68,0.71622,2,2,154.75,50.28,0.12823,3,71.21,45.53,0.87177,2,2,180.99,33.81,0,3,96.26,27.31,1,2,2,192.22,13.71,0,3,106.1,6.49,1,1,3,105.32,-12.21,1,1,3,104.48,-32.16,1,2,2,121.35,22.67,0.32,3,36.01,20.26,0.68,2,2,150.65,16.36,0.19204,3,64.81,11.97,0.80796,2,2,171.89,15.67,0.05097,3,85.95,9.84,0.94903,1,3,84.51,-14.67,1,1,3,85.77,-34.29,1,2,2,152.98,-35.01,0.112,3,63.63,-39.44,0.888,2,2,152.39,-12.54,0.06045,3,64.57,-16.98,0.93955,2,2,120.39,-14.3,0.33807,3,32.53,-16.56,0.66193,2,2,121.93,-49.39,0.40483,3,31.67,-51.67,0.59517,2,2,83.71,-60.56,0.79479,3,-7.22,-60.21,0.20521,2,2,78.87,-16.94,0.94472,3,-9.08,-16.36,0.05528,2,2,80,21.91,0.55499,3,-5.3,22.33,0.44501,1,2,36.59,20.46,1,1,2,34.35,-23.04,1,1,2,38.98,-70.06,1,1,2,-3.47,-25.88,1,1,2,-0.29,17.03,1,1,2,-0.09,-72.32,1,1,2,21.51,-108.72,1],"hull":23,"edges":[38,40,38,36,34,36,40,42,42,44,8,10,8,6,6,4,4,2,2,0,0,44,32,34,30,32,10,12,12,14,14,16,16,18,18,20,20,22,22,24,24,26,28,30,26,28],"width":182,"height":220}},"book_01":{"book_01":{"x":91.37,"y":-14.12,"rotation":-73.04,"width":159,"height":156}},"book_02":{"book_02":{"x":-11.17,"y":66.01,"width":171,"height":135}},"book_03":{"book_03":{"x":1.28,"y":54.33,"rotation":-0.01,"width":184,"height":109}},"book_04":{"book_04":{"x":3.83,"y":23.44,"rotation":-0.01,"width":181,"height":89}},"book_05":{"book_05":{"x":1.74,"y":23.45,"rotation":-0.01,"width":151,"height":92}},"book_06":{"book_06":{"x":-13.57,"y":22.88,"rotation":-0.01,"width":159,"height":64}},"box_01":{"box_01":{"type":"mesh","uvs":[1,0.22144,1,0.44889,1,0.57719,1,0.68405,0.93167,0.76707,0.78838,0.93312,0.70146,1,0.56408,1,0.41044,1,0.28066,1,0,0.86766,0,0.81741,0.03469,0.63388,0.0344,0.41169,0.02348,0.22689,0.01007,0,0.11411,0,0.18724,0,0.25519,0.01642,0.32315,0.0339,0.43809,0.0494,0.5899,0.07564,0.70918,0.09897,0.81959,0.05815,0.95465,0,1,0,0.07978,0.90043,0.1477,0.92884,0.19793,0.95506,0.68257,0.27976,0.64412,0.49263,0.64806,0.57719,0.64018,0.68799,0.76537,0.4693,0.7841,0.28851,0.96845,0.21852,0.93197,0.42556,0.9231,0.60926,0.77425,0.65884,0.57117,0.7259,0.56822,0.54511,0.56624,0.29142,0.4233,0.28851,0.41542,0.55386,0.40162,0.74923,0.29318,0.71424,0.31191,0.52178,0.31881,0.28559,0.23009,0.6705,0.1601,0.65592,0.09109,0.64134,0.10785,0.43139,0.17883,0.43431,0.25178,0.4693,0.25276,0.2506,0.17981,0.22727,0.11771,0.22436],"triangles":[55,51,56,51,13,56,14,15,16,14,16,56,13,14,56,35,25,0,35,24,25,23,24,35,34,23,35,34,22,23,46,53,47,53,52,47,52,54,47,52,51,55,56,16,17,52,55,54,54,55,18,54,18,19,47,54,19,47,19,20,55,17,18,55,56,17,42,46,47,42,47,20,42,20,21,41,42,21,43,46,42,40,42,41,29,41,21,29,21,22,29,22,34,30,29,33,36,34,35,36,35,0,36,0,1,33,34,36,40,41,30,36,1,2,31,30,33,40,30,31,37,33,36,37,36,2,12,13,51,50,12,51,52,50,51,49,52,53,48,49,53,49,50,52,38,33,37,31,33,38,46,48,53,37,2,3,32,40,31,32,31,38,45,48,46,45,46,43,39,40,32,43,40,39,44,45,43,39,44,43,4,37,3,38,37,4,50,10,11,12,50,11,26,50,49,26,10,50,27,26,49,27,49,48,27,48,45,5,38,4,32,38,5,28,27,45,9,28,45,44,9,45,26,27,28,9,26,28,10,26,9,7,8,44,9,44,8,39,7,44,6,39,32,6,7,39,32,5,6,40,43,42,30,41,29,33,29,34],"vertices":[2,1,223.95,53.13,0.66742,23,102.49,-11.85,0.33258,2,1,223.95,26.07,0.99246,23,102.49,-38.91,0.00754,1,1,223.95,10.8,1,1,1,223.95,-1.92,1,1,1,199.89,-11.8,1,1,1,149.45,-31.56,1,1,1,118.86,-39.51,1,1,1,70.5,-39.51,1,1,1,16.42,-39.51,1,1,1,-29.26,-39.51,1,1,1,-128.05,-23.77,1,1,1,-128.05,-17.79,1,2,1,-115.84,4.05,0.98412,21,-4.2,-69.58,0.01588,3,1,-115.95,30.49,0.3705,18,-89.45,-51.38,0.05753,21,-4.3,-43.14,0.57196,2,18,-93.29,-29.39,0.02717,21,-8.15,-21.15,0.97283,1,21,-12.87,5.85,1,2,18,-61.39,-2.39,0.5992,21,23.76,5.85,0.4008,1,18,-35.65,-2.39,1,1,18,-11.73,-4.34,1,2,19,-36.21,3.88,0.0679,18,12.19,-6.42,0.9321,3,19,4.25,2.03,0.55749,18,52.65,-8.27,0.43274,23,-95.31,8.63,0.00977,2,19,57.69,-1.09,0.88461,18,106.09,-11.39,0.11539,2,19,99.68,-3.87,0.59827,23,0.12,2.73,0.40173,1,23,38.98,7.59,1,1,23,86.52,14.5,1,1,23,102.49,14.5,1,1,1,-99.97,-27.67,1,1,1,-76.06,-31.05,1,1,1,-58.38,-34.17,1,3,1,112.21,46.19,0.46209,19,90.31,-25.38,0.31109,23,-9.25,-18.79,0.22683,3,1,98.68,20.86,0.82907,19,76.77,-50.71,0.08757,23,-22.78,-44.12,0.08335,3,1,100.06,10.8,0.96584,19,78.16,-60.78,0.03166,23,-21.4,-54.18,0.00251,2,1,97.29,-2.39,0.98762,23,-24.17,-67.37,0.01238,2,1,141.36,23.64,0.83694,23,19.9,-41.34,0.16306,2,1,147.95,45.15,0.67485,23,26.49,-19.83,0.32515,2,1,212.84,53.48,0.51368,23,91.38,-11.5,0.48632,2,1,200,28.84,0.8803,23,78.54,-36.14,0.1197,1,1,196.88,6.98,1,2,1,144.48,1.08,0.93997,23,23.02,-63.9,0.06003,3,1,73,-6.9,0.90092,19,51.1,-78.47,0.01959,23,-48.46,-71.88,0.07949,3,1,71.96,14.62,0.66607,19,50.06,-56.96,0.2093,23,-49.5,-50.36,0.12463,3,1,71.26,44.81,0.23871,19,49.36,-26.77,0.68699,18,97.76,-37.07,0.0743,4,1,20.95,45.15,0.15408,19,-0.95,-26.42,0.52808,18,47.45,-36.72,0.31766,23,-100.51,-19.83,1.8E-4,3,1,18.17,13.58,0.54946,19,-3.73,-58,0.39522,18,44.67,-68.3,0.05532,2,1,13.31,-9.67,0.88453,19,-8.59,-81.25,0.11547,2,1,-24.86,-5.51,0.96482,19,-46.76,-77.09,0.03518,3,1,-18.26,17.39,0.49563,19,-40.16,-54.18,0.30781,18,8.24,-64.48,0.19656,2,19,-37.74,-26.08,0.43204,18,10.67,-36.37,0.56796,1,1,-47.06,-0.3,1,3,1,-71.7,1.43,0.95433,18,-45.2,-80.44,0.01655,21,39.94,-72.2,0.02912,3,1,-95.99,3.17,0.91025,18,-69.49,-78.71,0.01264,21,15.65,-70.47,0.07711,3,1,-90.09,28.15,0.22449,18,-63.59,-53.72,0.14058,21,21.55,-45.48,0.63493,3,1,-65.11,27.8,0.16199,18,-38.61,-54.07,0.51215,21,46.54,-45.83,0.32587,4,1,-39.43,23.64,0.30863,19,-61.33,-47.94,0.15093,18,-12.93,-58.24,0.45991,21,72.21,-49.99,0.08053,3,19,-60.98,-21.91,0.0332,18,-12.58,-32.21,0.90042,21,72.56,-23.97,0.06638,2,18,-38.26,-29.43,0.86974,21,46.88,-21.19,0.13026,2,18,-60.12,-29.09,0.34886,21,25.02,-20.84,0.65114],"hull":26,"edges":[30,28,28,26,26,24,24,22,20,22,20,52,52,54,54,56,56,18,16,18,14,16,12,14,12,10,10,8,8,6,30,32,32,34,38,36,36,34,38,40,40,42,42,44,44,46,48,50,46,48,44,58,58,60,60,62,62,64,64,12,0,50,0,2,2,4,4,6,92,90,90,18,92,94,94,38,18,20],"width":352,"height":119}},"box_02":{"box_02":{"type":"mesh","uvs":[0.7924,0.16766,0.89042,0.3287,0.9834,0.53468,1,0.65452,0.89544,0.73317,0.72957,0.84552,0.55114,1,0.45313,1,0.3903,0.85676,0.2571,0.59086,0.12642,0.35492,0,0.16392,0,0.09276,0.18422,0.08152,0.37522,0.05905,0.57878,0,0.71701,0,0.39532,0.52345,0.27972,0.26878,0.45815,0.18639,0.65669,0.14519,0.77732,0.3699,0.57376,0.41858,0.6768,0.71819,0.52601,0.80433,0.87282,0.59835],"triangles":[4,25,3,25,2,3,23,25,4,24,8,17,24,17,23,25,23,22,17,22,23,22,19,20,20,16,0,19,15,20,18,13,14,20,15,16,11,12,13,19,14,15,10,11,13,18,14,19,10,13,18,21,20,0,22,18,19,22,20,21,10,18,17,22,17,18,9,10,17,21,0,1,8,9,17,25,22,21,7,24,6,6,24,5,7,8,24,24,23,5,5,23,4,2,21,1,2,25,21],"vertices":[1,23,118.93,-2.6,1,2,23,133.83,-19.02,0.74314,24,71.26,-28.37,0.25686,2,23,147.96,-40.03,0.33099,24,84.39,-50.02,0.66901,2,23,150.49,-52.26,0.31397,24,86.33,-62.35,0.68603,2,23,134.59,-60.28,0.51262,24,70.08,-69.62,0.48738,2,23,109.38,-71.74,0.63,24,44.35,-79.87,0.37,2,23,82.26,-87.5,0.62045,24,16.52,-94.34,0.37955,2,23,67.36,-87.5,0.56728,24,1.64,-93.63,0.43272,2,23,57.81,-72.88,0.59161,24,-7.21,-78.59,0.40839,2,23,37.56,-45.76,0.78046,24,-26.16,-50.54,0.21954,2,23,17.7,-21.7,0.86379,24,-44.87,-25.57,0.13621,1,23,-1.51,-2.21,1,1,23,-1.51,5.04,1,1,23,26.49,6.19,1,1,23,55.52,8.48,1,1,23,86.46,14.5,1,1,23,107.47,14.5,1,2,23,58.57,-38.89,0.9777,24,-4.85,-44.67,0.0223,1,23,41,-12.91,1,1,23,68.12,-4.51,1,1,23,98.3,-0.3,1,2,23,116.64,-23.22,0.95621,24,53.89,-31.76,0.04379,1,23,85.7,-28.19,1,2,23,101.36,-58.75,0.65822,24,36.95,-66.52,0.34178,2,23,78.44,-67.54,0.6715,24,13.64,-74.22,0.3285,2,23,131.15,-46.53,0.54281,24,67.29,-55.72,0.45719],"hull":17,"edges":[24,26,26,28,28,30,30,32,32,0,0,2,2,4,22,24,22,20,20,18,18,16,16,14,12,14,12,10,10,8,8,6,4,6],"width":152,"height":102}},"box_03":{"box_03":{"x":109.95,"y":38.99,"width":226,"height":91}},"box_04":{"box_04":{"type":"mesh","uvs":[0.37597,0.03188,0.6991,0.03321,0.96885,0.03431,0.9719,0.21735,0.97038,0.42027,0.97038,0.65503,0.96885,0.8878,0.75699,0.93753,0.48263,1,0.10311,1,0.10311,0.81419,0.04672,0.59336,0.02154,0.35531,0,0.15169,0,0.03034,0.45215,0.7545,0.74175,0.70874,0.72193,0.49985,0.70669,0.24719,0.3988,0.27305,0.43081,0.53566],"triangles":[17,4,5,6,16,5,7,16,6,15,16,7,8,15,7,20,19,17,11,12,20,10,11,20,15,10,20,8,9,10,8,10,15,20,17,16,15,20,16,16,17,5,12,19,20,19,18,17,3,1,2,3,18,1,19,0,1,19,1,18,13,0,19,13,14,0,12,13,19,4,18,3,17,18,4],"vertices":[1,1,-73.43,80.46,1,1,1,-33.37,80.33,1,1,1,0.08,80.23,1,2,1,0.46,62.84,0.87236,21,112.1,-10.79,0.12764,2,1,0.27,43.56,0.58975,21,111.92,-30.07,0.41025,2,1,0.27,21.26,0.34349,21,111.92,-52.37,0.65651,1,21,111.73,-74.49,1,1,21,85.46,-79.21,1,1,21,51.44,-85.15,1,1,21,4.37,-85.15,1,2,1,-107.27,6.14,0.20924,21,4.37,-67.49,0.79076,2,1,-114.26,27.12,0.37711,21,-2.62,-46.51,0.62289,2,1,-117.38,49.73,0.51453,21,-5.74,-23.9,0.48547,2,1,-120.05,69.07,0.81541,21,-8.41,-4.56,0.18459,2,1,-120.05,80.6,0.99679,21,-8.41,6.97,0.00321,2,1,-63.99,11.81,0.1655,21,47.66,-61.82,0.8345,2,1,-28.08,16.15,0.25811,21,83.57,-57.48,0.74189,2,1,-30.53,36,0.31677,21,81.11,-37.63,0.68323,2,1,-32.42,60,0.87793,21,79.22,-13.63,0.12207,2,1,-70.6,57.55,0.70939,21,41.04,-16.09,0.29061,2,1,-66.63,32.6,0.33392,21,45.01,-41.03,0.66608],"hull":15,"edges":[16,14,14,12,12,10,10,8,8,6,6,4,28,0,4,2,2,0,26,28,26,24,24,22,22,20,16,18,20,18],"width":124,"height":95}},"box_05":{"box_05":{"type":"mesh","uvs":[1,0.29834,0.94779,0.61642,0.93098,0.70966,0.79653,0.74805,0.6083,0.81934,0.47385,0.87967,0.11755,1,0,1,0,0.93451,0.06713,0.89612,0.15789,0.77547,0.23184,0.67127,0.29234,0.52319,0.35956,0.33125,0.41334,0.16123,0.4604,0,0.59149,0,0.68897,0,0.87384,0,1,0,0.31458,0.93346,0.55452,0.19414,0.49065,0.38609,0.37973,0.62739,0.27889,0.84128,0.68897,0.19414,0.83687,0.21059,0.84359,0.42448,0.64191,0.40254,0.61502,0.64933,0.82342,0.62739],"triangles":[26,28,25,28,26,27,25,16,17,12,13,22,22,21,28,13,14,22,22,14,21,14,15,21,21,15,16,28,21,25,21,16,25,27,26,0,0,26,19,26,18,19,25,17,26,26,17,18,23,12,22,11,12,23,30,28,27,1,27,0,30,27,1,23,22,29,29,28,30,6,8,9,24,6,9,3,29,30,20,24,5,4,5,23,5,24,23,4,29,3,3,30,2,6,24,20,10,11,24,24,11,23,4,23,29,2,30,1,24,9,10,6,7,8,29,22,28],"vertices":[2,26,53.8,-29.27,0.4365,21,73.59,-22.49,0.5635,1,26,44.3,-59.07,1,1,26,41.28,-67.8,1,1,26,20.29,-70.46,1,1,26,-9.17,-75.85,1,1,26,-30.26,-80.59,1,1,26,-85.96,-89.41,1,1,26,-104.16,-88.55,1,1,26,-103.87,-82.34,1,1,26,-93.3,-79.19,1,2,26,-78.71,-68.4,0.99339,21,-56.94,-67.81,0.00661,2,26,-66.8,-59.05,0.79617,21,-45.48,-57.92,0.20383,2,26,-56.77,-45.44,0.51333,21,-36.1,-43.85,0.48667,2,26,-45.5,-27.72,0.26985,21,-25.68,-25.61,0.73015,2,26,-36.41,-11.98,0.08939,21,-17.34,-9.46,0.91061,1,21,-10.05,5.85,1,1,21,10.27,5.85,1,1,21,25.38,5.85,1,2,26,35.61,-0.04,0.00597,21,54.03,5.85,0.99403,2,26,55.14,-0.96,0.00819,21,73.59,5.85,0.99181,1,26,-55.16,-84.54,1,2,26,-14.7,-16.13,0.13116,21,4.54,-12.59,0.86884,2,26,-25.45,-33.88,0.39616,21,-5.36,-30.82,0.60384,2,26,-43.7,-55.97,0.76738,21,-22.55,-53.75,0.23262,1,26,-60.27,-75.53,1,2,26,6.11,-17.11,0.14117,21,25.38,-12.59,0.85883,2,26,28.94,-19.75,0.21537,21,48.3,-14.15,0.78463,2,26,29.02,-40.1,0.67147,21,49.35,-34.47,0.32853,2,26,-2.1,-36.54,0.48616,21,18.09,-32.39,0.51384,1,26,-7.37,-59.77,1,1,26,24.99,-59.21,1],"hull":20,"edges":[30,28,28,26,26,24,24,22,22,20,20,18,14,16,18,16,12,14,10,8,8,6,6,4,4,2,0,38,2,0,10,12,30,32,32,34,34,36,36,38],"width":155,"height":95}},"ear_L":{"ear_L":{"x":17.29,"y":-3.51,"rotation":-116.65,"width":52,"height":70}},"ear_L-2":{"ear_L-2":{"x":20.22,"y":11.24,"rotation":-116.65,"width":55,"height":66}},"ear_R":{"ear_R":{"x":25.87,"y":5.16,"rotation":-84.46,"width":55,"height":83}},"ear_R-2":{"ear_R-2":{"x":23.79,"y":5.96,"rotation":-84.46,"width":57,"height":71}},"eye2_01":{"eye2_01":{"x":70.06,"y":3.41,"rotation":-88.83,"width":149,"height":84}},"eye2_02":{"eye2_02":{"x":57.07,"y":3.14,"rotation":-88.83,"width":127,"height":66}},"eye_01":{"eye_01":{"x":69.13,"y":0.39,"rotation":-88.83,"width":111,"height":62}},"eye_02":{"eye_02":{"x":76.16,"y":-1.47,"rotation":-88.83,"width":115,"height":68}},"eye_light":{"eye_light":{"x":-0.69,"y":4.36,"scaleX":0.415,"scaleY":0.495,"rotation":-88.83,"width":7,"height":9}},"eye_light2":{"eye_light":{"x":4.2,"y":-1.96,"scaleX":1.505,"scaleY":1.5,"rotation":-88.83,"width":7,"height":9}},"eye_light3":{"eye_light":{"x":6.86,"y":-1.96,"scaleX":1.635,"scaleY":1.63,"rotation":-88.83,"width":7,"height":9}},"eye_light4":{"eye_light":{"x":0.85,"y":2.91,"scaleX":0.515,"scaleY":0.525,"rotation":-88.83,"width":7,"height":9}},"face-02":{"face-02":{"x":27.98,"y":7.05,"rotation":-88.83,"width":60,"height":54}},"face_01":{"face_01":{"x":27.98,"y":7.05,"rotation":-88.83,"width":60,"height":54}},"face_effect":{"face_effect":{"x":37.93,"y":-1.71,"scaleX":1.71,"scaleY":1.71,"rotation":-88.83,"width":101,"height":46}},"hair_01":{"hair_01":{"x":18.99,"y":2.03,"rotation":40.49,"width":34,"height":29}},"hair_02":{"hair_02":{"x":9.89,"y":3.6,"rotation":92.86,"width":18,"height":27}},"hair_03":{"hair_03":{"x":21.76,"y":2.75,"rotation":153.43,"width":62,"height":33}},"hair_04":{"hair_04":{"x":14.07,"y":-3.62,"rotation":-120.7,"width":35,"height":41}},"hair_05":{"hair_05":{"x":11.75,"y":4.24,"rotation":-46.12,"width":24,"height":31}},"hand_L":{"hand_L":{"x":3.74,"y":1.92,"width":40,"height":39}},"hand_R":{"hand_R":{"x":-9.82,"y":-3.44,"width":47,"height":35}},"head":{"head":{"x":63.34,"y":-10.23,"rotation":-88.83,"width":166,"height":138}},"head2":{"head2":{"x":62.74,"y":-5.24,"rotation":-88.83,"width":162,"height":137}},"head_02":{"head_02":{"x":-4.11,"y":-6.96,"rotation":-88.83,"width":161,"height":86}},"head_02-2":{"head_02-2":{"x":-18.14,"y":-5.24,"rotation":-88.83,"width":159,"height":76}},"head_03":{"head_03":{"x":-19.65,"y":19.73,"rotation":-88.83,"width":83,"height":48}},"head_shadow-2":{"head_shadow-2":{"x":-29.93,"y":8.52,"rotation":-88.83,"width":55,"height":49}},"neck":{"neck":{"x":27.1,"y":-3.52,"rotation":-90,"width":66,"height":62}},"neck_02":{"neck_02":{"x":-11.9,"y":-5.52,"rotation":-90,"width":152,"height":80}},"shoulder_L":{"shoulder_L":{"x":34.08,"y":-1.74,"rotation":100.08,"width":60,"height":108}},"shoulder_R":{"shoulder_R":{"path":"shouler_R","x":45.37,"y":2.58,"rotation":85.41,"width":63,"height":129}},"sparkle":{"sparkle":{"x":0.79,"y":1.38,"scaleX":0.8,"scaleY":0.8,"width":86,"height":65}},"tail":{"tail":{"type":"mesh","uvs":[0.84488,0.05174,0.92429,0.10481,1,0.20299,1,0.31178,1,0.41526,0.9094,0.5612,0.77044,0.63815,0.6017,0.69388,0.38829,0.76287,0.29896,0.80532,0.22451,0.86635,0.14014,1,0,1,0,0.81594,0.08059,0.7151,0.15999,0.65408,0.29399,0.61162,0.44784,0.57182,0.60666,0.51079,0.69103,0.44976,0.76051,0.36485,0.7357,0.27994,0.68607,0.18972,0.55207,0.1393,0.38333,0.14726,0.2791,0.21095,0.30392,0.29586,0.30888,0.35423,0.21459,0.38077,0.08059,0.37015,0,0.30116,0,0.23217,0.08555,0.11808,0.19473,0.04909,0.37836,0,0.67614,0],"triangles":[27,28,26,26,28,25,25,28,29,21,2,3,32,25,29,32,29,31,31,29,30,21,1,2,21,0,1,21,22,0,32,33,25,25,33,24,23,35,22,22,35,0,33,34,24,24,34,23,23,34,35,20,21,3,9,16,8,8,17,7,8,16,17,7,18,6,7,17,18,18,19,6,6,19,5,19,20,5,5,20,4,20,3,4,10,11,13,11,12,13,13,14,10,14,15,10,10,15,9,15,16,9],"vertices":[2,31,132.15,78.11,0.32114,32,21.45,14.27,0.67886,2,31,133.46,64.45,0.27058,32,22.76,0.6,0.72942,2,31,129.44,43.37,0.28155,32,18.74,-20.47,0.71845,2,31,117.4,24.99,0.474,32,6.71,-38.86,0.526,2,31,105.96,7.49,0.69488,32,-4.74,-56.35,0.30512,2,31,81.63,-11.81,0.98962,32,-29.07,-75.66,0.01038,1,31,60.56,-16.6,1,1,31,39.15,-16.04,1,2,30,54.5,-19.67,0.00447,31,12.23,-15.08,0.99553,2,30,42.69,-14.48,0.46609,31,-0.54,-16.98,0.53391,2,30,28.13,-12.31,0.966,31,-14.02,-22.89,0.034,1,30,-0.21,-15.28,1,1,30,-6.52,-1.53,1,1,30,27.28,13.97,1,1,30,49.42,14.56,1,2,30,64.2,11.9,0.95624,31,3.63,16.81,0.04376,2,30,78.03,2.32,0.26085,31,20.44,16.06,0.73915,2,30,92.26,-9.43,0.00626,31,38.74,13.69,0.99374,2,31,59.85,14.61,0.99539,32,-50.85,-49.23,0.00461,2,31,74.22,19.94,0.90743,32,-36.48,-43.91,0.09257,2,31,89.89,30.18,0.70986,32,-20.81,-33.66,0.29014,2,31,97.04,46,0.52036,32,-13.66,-17.84,0.47964,2,31,102.54,64.18,0.41646,32,-8.16,0.34,0.58354,2,31,96,80.63,0.50564,32,-14.7,16.79,0.49436,2,31,79.87,89.26,0.39478,32,-30.83,25.42,0.60522,2,31,63.41,84.66,0.20866,32,-47.29,20.82,0.79134,2,31,56.26,68.84,0.11117,32,-54.44,5,0.88883,2,31,50.25,58.68,0.02602,32,-60.45,-5.16,0.97398,1,32,-71.9,-4.07,1,1,32,-82.84,5.65,1,1,32,-82.49,22.08,1,2,31,35.84,97.58,0.0288,32,-74.86,33.74,0.9712,2,31,56.19,111.81,0.16932,32,-54.51,47.96,0.83068,2,31,73.69,117.01,0.24415,32,-37.01,53.17,0.75585,2,31,95.71,114.45,0.27076,32,-14.99,50.6,0.72924,2,31,122.62,96.84,0.35911,32,11.92,32.99,0.64089],"hull":36,"edges":[22,24,22,20,20,18,18,16,16,14,14,12,12,10,10,8,24,26,26,28,28,30,30,32,32,34,34,36,36,38,38,40,40,42,42,44,44,46,46,48,48,50,50,52,52,54,54,56,56,58,58,60,60,62,62,64,64,66,66,68,68,70,70,0,0,2,2,4,4,6,6,8],"width":108,"height":202}}}}],"animations":{"Emotion":{"slots":{"ear_L":{"color":[{"color":"ffffff00"}]},"ear_L-2":{"color":[{"color":"ffffffff"}]},"ear_R":{"color":[{"color":"ffffff00"}]},"ear_R-2":{"color":[{"color":"ffffffff"}]},"eye2_01":{"color":[{"time":0.8333,"color":"ffffff00","curve":"stepped"},{"time":0.8667,"color":"ffffffff","curve":"stepped"},{"time":1.0333,"color":"ffffffff","curve":"stepped"},{"time":1.0667,"color":"ffffff00"}]},"eye2_02":{"color":[{"time":0.8667,"color":"ffffff00","curve":"stepped"},{"time":0.9,"color":"ffffffff","curve":"stepped"},{"time":1,"color":"ffffffff","curve":"stepped"},{"time":1.0333,"color":"ffffff00"}]},"face-02":{"color":[{"time":0.3667,"color":"ffffff00","curve":0.25,"c3":0.75},{"time":0.4,"color":"ffffffff","curve":0.25,"c3":0.75},{"time":0.5333,"color":"ffffff00","curve":"stepped"},{"time":0.6333,"color":"ffffff00","curve":0.25,"c3":0.75},{"time":0.6667,"color":"ffffffff","curve":0.25,"c3":0.75},{"time":0.8,"color":"ffffff00"}]},"face_01":{"color":[{"color":"ffffffff","curve":0.25,"c3":0.75},{"time":0.2667,"color":"ffffff00","curve":0.25,"c3":0.75},{"time":0.5,"color":"ffffffff","curve":0.25,"c3":0.75},{"time":0.5333,"color":"ffffff00","curve":0.25,"c3":0.75},{"time":0.7667,"color":"ffffffff"}]},"head":{"color":[{"color":"ffffff00"}]},"head2":{"color":[{"color":"ffffffff"}]},"head_02":{"color":[{"color":"ffffff00"}]},"head_02-2":{"color":[{"color":"ffffffff"}]},"head_03":{"color":[{"color":"ffffff00"}]},"head_shadow-2":{"color":[{"color":"ffffffff"}]}},"bones":{"body_01":{"translate":[{"curve":0.25,"c3":0.75},{"time":0.8333,"y":-1.91,"curve":0.25,"c3":0.75},{"time":1.6667}]},"body_02":{"translate":[{"curve":0.25,"c3":0.75},{"time":0.8333,"x":-2.71,"y":-0.07,"curve":0.25,"c3":0.75},{"time":1.6667}]},"shoulder_L":{"translate":[{"curve":0.25,"c3":0.75},{"time":0.8333,"x":2.9,"y":-0.12,"curve":0.25,"c3":0.75},{"time":1.6667}]},"hand_L":{"translate":[{"curve":0.25,"c3":0.625,"c4":0.5},{"time":0.8333,"x":0.76,"y":-0.22,"curve":0.375,"c2":0.5,"c3":0.75},{"time":1.6667}]},"shoulder_R":{"translate":[{"curve":0.25,"c3":0.75},{"time":0.8333,"x":3.55,"y":-0.15,"curve":0.25,"c3":0.75},{"time":1.6667}]},"hand_L2":{"translate":[{"curve":0.25,"c3":0.625,"c4":0.5},{"time":0.8333,"y":-1.68,"curve":0.375,"c2":0.5,"c3":0.75},{"time":1.6667}]},"head":{"rotate":[{"curve":0.266,"c3":0.618,"c4":0.42},{"time":0.5333,"angle":2.52,"curve":0.325,"c2":0.31,"c3":0.682,"c4":0.72},{"time":1.2,"angle":-3.44,"curve":0.381,"c2":0.59,"c3":0.728},{"time":1.6667}],"translate":[{"curve":0.25,"c3":0.75},{"time":0.8333,"x":-1.55,"curve":0.25,"c3":0.75},{"time":1.6667}]},"hand_R":{"translate":[{"curve":0.25,"c3":0.625,"c4":0.5},{"time":0.8333,"x":0.08,"y":0.06,"curve":0.375,"c2":0.5,"c3":0.75},{"time":1.6667}]},"hand_R2":{"translate":[{"curve":0.25,"c3":0.625,"c4":0.5},{"time":0.8333,"y":-1.68,"curve":0.375,"c2":0.5,"c3":0.75},{"time":1.6667}]},"ear_R":{"rotate":[{"time":0.8667,"curve":0.334,"c2":0.33,"c3":0.668,"c4":0.67},{"time":0.9667,"angle":-15,"curve":0.335,"c2":0.34,"c3":0.668,"c4":0.67},{"time":1.0333,"angle":4.8,"curve":0.381,"c2":0.55,"c3":0.742},{"time":1.1333}],"translate":[{"x":-3.5,"y":-1.48}]},"ear_L":{"rotate":[{"time":0.8667,"curve":0.334,"c2":0.33,"c3":0.668,"c4":0.67},{"time":0.9667,"angle":21.3,"curve":0.335,"c2":0.34,"c3":0.668,"c4":0.67},{"time":1.0333,"angle":-10.5,"curve":0.381,"c2":0.55,"c3":0.742},{"time":1.1333}],"translate":[{"x":-1.5,"y":4.44}]},"hair_04":{"rotate":[{"curve":0.25,"c3":0.75},{"time":0.8333,"angle":-5.1,"curve":0.25,"c3":0.75},{"time":1.6667}]},"hair_01":{"rotate":[{"curve":0.25,"c3":0.75},{"time":0.8333,"angle":-4.5,"curve":0.25,"c3":0.75},{"time":1.6667}]},"hair_02":{"rotate":[{"curve":0.25,"c3":0.75},{"time":0.8333,"angle":-6.6,"curve":0.25,"c3":0.75},{"time":1.6667}]},"hair_05":{"rotate":[{"curve":0.25,"c3":0.75},{"time":0.8333,"angle":5.1,"curve":0.25,"c3":0.75},{"time":1.6667}]},"tail_01":{"rotate":[{"curve":0.25,"c3":0.625,"c4":0.5},{"time":0.8333,"angle":-1.3,"curve":0.375,"c2":0.5,"c3":0.75},{"time":1.6667}]},"tail_02":{"rotate":[{"curve":0.25,"c3":0.625,"c4":0.5},{"time":0.8333,"angle":-16.16,"curve":0.375,"c2":0.5,"c3":0.75},{"time":1.6667}]},"tail_03":{"rotate":[{"curve":0.274,"c3":0.62,"c4":0.4},{"time":0.4333,"angle":-14.4,"curve":0.315,"c2":0.27,"c3":0.677,"c4":0.7},{"time":1.1667,"angle":20.82,"curve":0.382,"c2":0.58,"c3":0.731},{"time":1.6667}],"translate":[{"curve":0.274,"c3":0.62,"c4":0.4},{"time":0.4333,"x":3.93,"y":-1.95,"curve":0.315,"c2":0.27,"c3":0.677,"c4":0.7},{"time":1.1667,"x":-5.13,"y":2.32,"curve":0.382,"c2":0.58,"c3":0.731},{"time":1.6667}]},"galss":{"translate":[{"x":-3.81,"y":-0.77}]},"box_02":{"rotate":[{},{"time":0.8333,"angle":-8.7},{"time":1.6667}]},"hair_03":{"rotate":[{"curve":0.25,"c3":0.75},{"time":0.8333,"angle":4.8,"curve":0.25,"c3":0.75},{"time":1.6667}]},"Center":{"translate":[{"curve":0.25,"c3":0.75},{"time":0.8333,"y":-1.21,"curve":0.375,"c2":0.5,"c3":0.75},{"time":1.6667}],"scale":[{"curve":0.25,"c3":0.625,"c4":0.5},{"time":0.8333,"x":0.989,"y":0.989,"curve":0.375,"c2":0.5,"c3":0.75},{"time":1.6667}]},"box_05":{"rotate":[{},{"time":0.8333,"angle":7.8},{"time":1.6667}]},"book":{"rotate":[{},{"time":0.5333,"angle":1.01},{"time":1.1667,"angle":-0.6},{"time":1.6667}],"scale":[{},{"time":0.8333,"x":0.989,"y":0.989,"curve":0.375,"c2":0.5,"c3":0.75},{"time":1.6667}]},"book_01":{"rotate":[{},{"time":0.8333,"angle":-1.2},{"time":1.6667}],"scale":[{},{"time":0.8333,"x":0.989,"y":0.989,"curve":0.375,"c2":0.5,"c3":0.75},{"time":1.6667}]},"book_02":{"rotate":[{},{"time":0.4,"angle":-0.5},{"time":1.2333,"angle":1.61},{"time":1.6667}],"scale":[{},{"time":0.8333,"x":0.989,"y":0.989,"curve":0.375,"c2":0.5,"c3":0.75},{"time":1.6667}]},"book_06":{"rotate":[{"angle":3.9,"curve":0.25,"c3":0.75},{"time":0.8333,"curve":0.25,"c3":0.75},{"time":1.6667,"angle":3.9}]},"book_05":{"rotate":[{"angle":1.73},{"time":0.4},{"time":1.2333,"angle":3.6},{"time":1.6667,"angle":1.73}]},"book_04":{"rotate":[{},{"time":0.8333,"angle":3.6},{"time":1.6667}]}},"drawOrder":[{"offsets":[{"slot":"arm_R_01","offset":1}]}]},"Emotion_02":{"slots":{"ear_L":{"color":[{"color":"ffffff00"}]},"ear_L-2":{"color":[{"color":"ffffffff"}]},"ear_R":{"color":[{"color":"ffffff00"}]},"ear_R-2":{"color":[{"color":"ffffffff"}]},"eye2_01":{"color":[{"time":0.8333,"color":"ffffff00","curve":"stepped"},{"time":0.8667,"color":"ffffffff","curve":"stepped"},{"time":1.0333,"color":"ffffffff","curve":"stepped"},{"time":1.0667,"color":"ffffff00"}]},"eye2_02":{"color":[{"time":0.8667,"color":"ffffff00","curve":"stepped"},{"time":0.9,"color":"ffffffff","curve":"stepped"},{"time":1,"color":"ffffffff","curve":"stepped"},{"time":1.0333,"color":"ffffff00"}]},"face-02":{"color":[{"time":0.3667,"color":"ffffff00","curve":0.25,"c3":0.75},{"time":0.4,"color":"ffffffff","curve":0.25,"c3":0.75},{"time":0.5333,"color":"ffffff00","curve":"stepped"},{"time":0.6333,"color":"ffffff00","curve":0.25,"c3":0.75},{"time":0.6667,"color":"ffffffff","curve":0.25,"c3":0.75},{"time":0.8,"color":"ffffff00"}]},"face_01":{"color":[{"color":"ffffffff","curve":0.25,"c3":0.75},{"time":0.2667,"color":"ffffff00","curve":0.25,"c3":0.75},{"time":0.5,"color":"ffffffff","curve":0.25,"c3":0.75},{"time":0.5333,"color":"ffffff00","curve":0.25,"c3":0.75},{"time":0.7667,"color":"ffffffff"}]},"head":{"color":[{"color":"ffffff00"}]},"head2":{"color":[{"color":"ffffffff"}]},"head_02":{"color":[{"color":"ffffff00"}]},"head_02-2":{"color":[{"color":"ffffffff"}]},"head_03":{"color":[{"color":"ffffff00"}]},"head_shadow-2":{"color":[{"color":"ffffffff"}]}},"bones":{"hair_03":{"rotate":[{"curve":0.25,"c3":0.75},{"time":0.8333,"angle":4.8,"curve":0.25,"c3":0.75},{"time":1.6667}]},"Center":{"translate":[{"curve":0.25,"c3":0.625,"c4":0.5},{"time":0.8333,"y":-1.21,"curve":0.375,"c2":0.5,"c3":0.75},{"time":1.6667}],"scale":[{"curve":0.25,"c3":0.625,"c4":0.5},{"time":0.8333,"x":0.989,"y":0.989,"curve":0.375,"c2":0.5,"c3":0.75},{"time":1.6667}]},"body_01":{"translate":[{"curve":0.25,"c3":0.75},{"time":0.8333,"y":-1.91,"curve":0.25,"c3":0.75},{"time":1.6667}]},"body_02":{"translate":[{"curve":0.25,"c3":0.75},{"time":0.8333,"x":-2.71,"y":-0.07,"curve":0.25,"c3":0.75},{"time":1.6667}]},"shoulder_L":{"translate":[{"curve":0.25,"c3":0.75},{"time":0.8333,"x":2.9,"y":-0.12,"curve":0.25,"c3":0.75},{"time":1.6667}]},"arm_R":{"rotate":[{"angle":-127.8,"curve":0.258,"c3":0.619,"c4":0.45},{"time":0.6667,"angle":-135,"curve":0.363,"c2":0.44,"c3":0.755},{"time":1.6667,"angle":-127.8}],"translate":[{"x":3.83,"y":-7.24}]},"galss":{"translate":[{"x":-3.81,"y":-0.77}]},"box_02":{"rotate":[{},{"time":0.8333,"angle":-8.7},{"time":1.6667}]},"hand_L":{"translate":[{"curve":0.25,"c3":0.625,"c4":0.5},{"time":0.8333,"x":0.76,"y":-0.22,"curve":0.375,"c2":0.5,"c3":0.75},{"time":1.6667}]},"head":{"rotate":[{"curve":0.266,"c3":0.618,"c4":0.42},{"time":0.5333,"angle":2.52,"curve":0.325,"c2":0.31,"c3":0.682,"c4":0.72},{"time":1.2,"angle":-3.44,"curve":0.381,"c2":0.59,"c3":0.728},{"time":1.6667}],"translate":[{"curve":0.25,"c3":0.75},{"time":0.8333,"x":-1.55,"curve":0.262,"c3":0.618,"c4":0.44},{"time":1.1333,"x":-1.06,"curve":0.356,"c2":0.42,"c3":0.756},{"time":1.6667}]},"ear_R":{"rotate":[{"time":0.8667,"curve":0.334,"c2":0.33,"c3":0.668,"c4":0.67},{"time":0.9667,"angle":-15,"curve":0.335,"c2":0.34,"c3":0.668,"c4":0.67},{"time":1.0333,"angle":4.8,"curve":0.381,"c2":0.55,"c3":0.742},{"time":1.1333}],"translate":[{"x":-3.5,"y":-1.48}]},"ear_L":{"rotate":[{"time":0.8667,"curve":0.334,"c2":0.33,"c3":0.668,"c4":0.67},{"time":0.9667,"angle":21.3,"curve":0.335,"c2":0.34,"c3":0.668,"c4":0.67},{"time":1.0333,"angle":-10.5,"curve":0.381,"c2":0.55,"c3":0.742},{"time":1.1333}],"translate":[{"x":-1.5,"y":4.44}]},"hand_L2":{"translate":[{"curve":0.25,"c3":0.625,"c4":0.5},{"time":0.8333,"y":-1.68,"curve":0.375,"c2":0.5,"c3":0.75},{"time":1.6667}]},"shoulder_R":{"translate":[{"curve":0.25,"c3":0.75},{"time":0.8333,"x":3.55,"y":-0.15,"curve":0.25,"c3":0.75},{"time":1.6667}]},"hand_R":{"rotate":[{"curve":0.25,"c3":0.625,"c4":0.5},{"time":0.8333,"angle":11.1,"curve":0.375,"c2":0.5,"c3":0.75},{"time":1.6667}],"translate":[{"curve":0.25,"c3":0.625,"c4":0.5},{"time":0.8333,"x":0.08,"y":0.06,"curve":0.375,"c2":0.5,"c3":0.75},{"time":1.6667}]},"hand_R2":{"translate":[{"curve":0.25,"c3":0.625,"c4":0.5},{"time":0.8333,"y":-1.68,"curve":0.375,"c2":0.5,"c3":0.75},{"time":1.6667}]},"hair_04":{"rotate":[{"curve":0.25,"c3":0.75},{"time":0.8333,"angle":-5.1,"curve":0.25,"c3":0.75},{"time":1.6667}]},"hair_01":{"rotate":[{"curve":0.25,"c3":0.75},{"time":0.8333,"angle":-4.5,"curve":0.25,"c3":0.75},{"time":1.6667}]},"hair_02":{"rotate":[{"curve":0.25,"c3":0.75},{"time":0.8333,"angle":-6.6,"curve":0.25,"c3":0.75},{"time":1.6667}]},"hair_05":{"rotate":[{"curve":0.25,"c3":0.75},{"time":0.8333,"angle":5.1,"curve":0.25,"c3":0.75},{"time":1.6667}]},"tail_01":{"rotate":[{"curve":0.25,"c3":0.625,"c4":0.5},{"time":0.8333,"angle":-1.3,"curve":0.375,"c2":0.5,"c3":0.75},{"time":1.6667}]},"tail_02":{"rotate":[{"curve":0.25,"c3":0.625,"c4":0.5},{"time":0.8333,"angle":-16.16,"curve":0.375,"c2":0.5,"c3":0.75},{"time":1.6667}]},"tail_03":{"rotate":[{"curve":0.274,"c3":0.62,"c4":0.4},{"time":0.4333,"angle":-14.4,"curve":0.315,"c2":0.27,"c3":0.677,"c4":0.7},{"time":1.1667,"angle":20.82,"curve":0.382,"c2":0.58,"c3":0.731},{"time":1.6667}],"translate":[{"curve":0.274,"c3":0.62,"c4":0.4},{"time":0.4333,"x":3.93,"y":-1.95,"curve":0.315,"c2":0.27,"c3":0.677,"c4":0.7},{"time":1.1667,"x":-5.13,"y":2.32,"curve":0.382,"c2":0.58,"c3":0.731},{"time":1.6667}]},"box_05":{"rotate":[{},{"time":0.8333,"angle":7.8},{"time":1.6667}]},"book":{"rotate":[{},{"time":0.5333,"angle":1.01},{"time":1.1667,"angle":-0.6},{"time":1.6667}],"scale":[{},{"time":0.8333,"x":0.989,"y":0.989,"curve":0.375,"c2":0.5,"c3":0.75},{"time":1.6667}]},"book_01":{"rotate":[{},{"time":0.8333,"angle":-1.2},{"time":1.6667}],"scale":[{},{"time":0.8333,"x":0.989,"y":0.989,"curve":0.375,"c2":0.5,"c3":0.75},{"time":1.6667}]},"book_02":{"rotate":[{},{"time":0.4,"angle":-0.5},{"time":1.2333,"angle":1.61},{"time":1.6667}],"scale":[{},{"time":0.8333,"x":0.989,"y":0.989,"curve":0.375,"c2":0.5,"c3":0.75},{"time":1.6667}]},"book_06":{"rotate":[{"angle":3.9,"curve":0.25,"c3":0.75},{"time":0.8333,"curve":0.25,"c3":0.75},{"time":1.6667,"angle":3.9}]},"book_05":{"rotate":[{"angle":1.73},{"time":0.4},{"time":1.2333,"angle":3.6},{"time":1.6667,"angle":1.73}]},"book_04":{"rotate":[{},{"time":0.8333,"angle":3.6},{"time":1.6667}]}},"drawOrder":[{"offsets":[{"slot":"arm_R_01","offset":3},{"slot":"hand_R","offset":-29}]},{"time":1.6667,"offsets":[{"slot":"arm_R_01","offset":1}]}]},"Emotion_03":{"slots":{"ear_L":{"color":[{"color":"ffffff00"}]},"ear_L-2":{"color":[{"color":"ffffffff"}]},"ear_R":{"color":[{"color":"ffffff00"}]},"ear_R-2":{"color":[{"color":"ffffffff"}]},"eye2_01":{"color":[{"time":0.5,"color":"ffffff00","curve":"stepped"},{"time":0.5333,"color":"ffffffff","curve":"stepped"},{"time":0.6667,"color":"ffffffff","curve":"stepped"},{"time":0.7,"color":"ffffff00"}]},"eye2_02":{"color":[{"time":0.5333,"color":"ffffff00","curve":"stepped"},{"time":0.5667,"color":"ffffffff","curve":"stepped"},{"time":0.6333,"color":"ffffffff","curve":"stepped"},{"time":0.6667,"color":"ffffff00"}]},"face_01":{"color":[{"color":"ffffffff"}]},"head":{"color":[{"color":"ffffff00"}]},"head2":{"color":[{"color":"ffffffff"}]},"head_02":{"color":[{"color":"ffffff00"}]},"head_02-2":{"color":[{"color":"ffffffff"}]},"head_03":{"color":[{"color":"ffffff00"}]},"head_shadow-2":{"color":[{"color":"ffffffff"}]}},"bones":{"box_02":{"rotate":[{"time":0.2333},{"time":0.4667,"angle":-16.8},{"time":0.7,"angle":33.3},{"time":0.9,"angle":-5.83},{"time":1.1333}]},"hair_03":{"rotate":[{"time":0.3333},{"time":0.5667,"angle":7.5},{"time":0.8333,"angle":-12.9},{"time":1.0333}]},"Center":{"translate":[{"curve":0.258,"c3":0.619,"c4":0.45},{"time":0.3333,"y":-2.76,"curve":0.334,"c2":0.34,"c3":0.683,"c4":0.72},{"time":0.6,"y":2.99,"curve":0.381,"c2":0.59,"c3":0.728},{"time":0.8333}],"scale":[{"curve":0.258,"c3":0.619,"c4":0.45},{"time":0.3333,"y":0.975,"curve":0.334,"c2":0.34,"c3":0.683,"c4":0.72},{"time":0.6,"y":1.005,"curve":0.381,"c2":0.59,"c3":0.728},{"time":0.8333}]},"body_01":{"translate":[{"curve":0.25,"c3":0.75},{"time":0.3333,"y":-5.21},{"time":0.6,"y":4.23},{"time":0.8333}]},"body_02":{"rotate":[{"time":0.6},{"time":0.8333,"angle":3.3},{"time":1.1667,"angle":0.48},{"time":1.4333}],"translate":[{"curve":0.25,"c3":0.75},{"time":0.3333,"x":-2.58,"y":-0.07},{"time":0.6,"x":1.11,"y":0.03},{"time":0.8333}]},"nack":{"rotate":[{"time":0.3333},{"time":0.6,"angle":-2.1},{"time":0.8333,"angle":3},{"time":1.1,"angle":2.61},{"time":1.4333}],"translate":[{"curve":0.25,"c3":0.75},{"time":0.3333,"x":-1.27,"y":0.05},{"time":0.6,"x":1.05,"y":-0.04},{"time":0.8333}]},"shoulder_L":{"rotate":[{"time":0.6},{"time":0.8333,"angle":-1.2},{"time":1.4333}]},"head":{"rotate":[{"curve":0.266,"c3":0.618,"c4":0.42},{"time":0.3333,"angle":-1.56},{"time":0.6,"angle":-3.3},{"time":0.8667,"angle":13.5,"curve":0.334,"c3":0.669,"c4":0.36},{"time":1.1667,"angle":9.83,"curve":0.25,"c3":0.75},{"time":1.4333}],"translate":[{"curve":0.25,"c3":0.75},{"time":0.3333,"x":-1.59},{"time":0.6,"x":0.83},{"time":0.8667}]},"galss":{"translate":[{"x":-3.81,"y":-0.77}]},"ear_L":{"rotate":[{"time":0.6333,"curve":0.334,"c2":0.33,"c3":0.668,"c4":0.67},{"time":0.7,"angle":-6,"curve":0.335,"c2":0.34,"c3":0.668,"c4":0.67},{"time":0.8333,"angle":15.3,"curve":0.381,"c2":0.55,"c3":0.742},{"time":0.9}],"translate":[{"x":-1.5,"y":4.44}]},"ear_R":{"rotate":[{"time":0.6333,"curve":0.334,"c2":0.33,"c3":0.668,"c4":0.67},{"time":0.7,"angle":3,"curve":0.335,"c2":0.34,"c3":0.668,"c4":0.67},{"time":0.8333,"angle":-18.9,"curve":0.381,"c2":0.55,"c3":0.742},{"time":0.9}],"translate":[{"x":-3.5,"y":-1.48}]},"shoulder_R":{"rotate":[{"time":0.6},{"time":0.8333,"angle":0.3},{"time":1.4333}]},"tail_03":{"rotate":[{"curve":0.274,"c3":0.62,"c4":0.4},{"time":0.4333,"angle":20.82,"curve":0.382,"c2":0.58,"c3":0.731},{"time":1.0667,"angle":-14.4,"curve":0.315,"c2":0.27,"c3":0.677,"c4":0.7},{"time":1.4333}],"translate":[{"curve":0.274,"c3":0.62,"c4":0.4},{"time":0.4333,"x":-5.13,"y":2.32,"curve":0.382,"c2":0.58,"c3":0.731},{"time":1.0667,"x":3.93,"y":-1.95,"curve":0.315,"c2":0.27,"c3":0.677,"c4":0.7},{"time":1.4333}]},"hand_L2":{"translate":[{"curve":0.25,"c3":0.625,"c4":0.5},{"time":0.3333,"y":-6.99},{"time":0.6,"y":4.71},{"time":0.8333}]},"hand_R2":{"translate":[{"curve":0.25,"c3":0.625,"c4":0.5},{"time":0.3333,"y":-6.03},{"time":0.6,"y":7.26},{"time":0.8333}]},"hair_04":{"rotate":[{"time":0.3333},{"time":0.5667,"angle":19.5},{"time":0.8333,"angle":-11.1},{"time":1.0333}]},"hair_01":{"rotate":[{"time":0.3333},{"time":0.5667,"angle":-8.4},{"time":0.8333,"angle":14.1},{"time":1.0333}]},"hair_02":{"rotate":[{"time":0.3333},{"time":0.5667,"angle":-5.4},{"time":0.8333,"angle":17.1},{"time":1.0333}]},"hair_05":{"rotate":[{"time":0.3333},{"time":0.5667,"angle":-13.5},{"time":0.8333,"angle":16.5},{"time":1.0333}]},"tail_01":{"rotate":[{"curve":0.25,"c3":0.625,"c4":0.5},{"time":0.4,"angle":4.05},{"time":0.6333,"angle":10.58},{"time":0.8333,"angle":-0.9},{"time":1.0667}]},"tail_02":{"rotate":[{"curve":0.25,"c3":0.625,"c4":0.5},{"time":0.4,"angle":-3.49},{"time":0.6333,"angle":-2.32},{"time":0.8333,"angle":-11.72},{"time":1.0667}]},"box_05":{"rotate":[{"time":0.2333},{"time":0.5,"angle":10.5},{"time":0.7,"angle":-13.5},{"time":0.9,"angle":4.2},{"time":1.0667}],"translate":[{"time":0.5},{"time":0.7,"x":0.55},{"time":0.9}]},"box_01-R":{"rotate":[{},{"time":0.3333,"angle":2.7},{"time":0.6,"angle":-2.7},{"time":0.8333}],"translate":[{},{"time":0.3333,"y":-3.85},{"time":0.6,"y":5.49},{"time":0.8333}]},"box_01-L":{"rotate":[{},{"time":0.3333,"angle":4.5},{"time":0.6}],"translate":[{},{"time":0.3333,"y":-2.59},{"time":0.6,"y":3.86},{"time":0.8333}]},"book":{"scale":[{},{"time":0.4333,"y":0.905},{"time":0.6333,"y":1.05},{"time":0.8333,"y":0.905},{"time":1}]},"book_04":{"translate":[{"time":0.4333},{"time":0.6333,"y":5.86},{"time":0.8333,"y":-5.13},{"time":1,"y":2.81},{"time":1.2}]},"book_05":{"translate":[{"time":0.4333},{"time":0.6333,"y":5.32},{"time":0.8333,"y":-2.67},{"time":1,"y":5.23},{"time":1.2}]},"book_06":{"translate":[{"time":0.4333},{"time":0.6333,"y":6.43},{"time":0.8333,"y":-1.33},{"time":1,"y":2.01},{"time":1.1333,"y":3.22},{"time":1.2667}]},"book_01":{"translate":[{},{"time":0.3667,"y":-3.62},{"time":0.5667,"x":1.21,"y":3.22},{"time":0.7667,"x":-0.4,"y":-4.02},{"time":0.9333}]},"book_02":{"scale":[{},{"time":0.3667,"y":0.905},{"time":0.5667,"y":1.05},{"time":0.7667,"y":0.905},{"time":0.9333}]}}},"Emotion_04":{"slots":{"ear_L":{"color":[{"color":"ffffff00"}]},"ear_L-2":{"color":[{"color":"ffffffff"}]},"ear_R":{"color":[{"color":"ffffff00"}]},"ear_R-2":{"color":[{"color":"ffffffff"}]},"eye2_01":{"color":[{"time":0.4,"color":"ffffff00","curve":"stepped"},{"time":0.4333,"color":"ffffffff","curve":"stepped"},{"time":0.6667,"color":"ffffffff","curve":"stepped"},{"time":0.7,"color":"ffffff00"}]},"eye2_02":{"color":[{"time":0.4333,"color":"ffffff00","curve":"stepped"},{"time":0.4667,"color":"ffffffff","curve":"stepped"},{"time":0.6333,"color":"ffffffff","curve":"stepped"},{"time":0.6667,"color":"ffffff00"}]},"eye_light":{"color":[{"time":0.6667,"color":"ffffff00"},{"time":0.7,"color":"ffffffff","curve":"stepped"},{"time":1.4667,"color":"ffffffff"},{"time":1.5667,"color":"ffffff00"}]},"eye_light2":{"color":[{"time":0.7667,"color":"ffffffff"}],"color":[{"time":0.6667,"color":"ffffff00"},{"time":0.7,"color":"ffffffff","curve":"stepped"},{"time":1.4667,"color":"ffffffff"},{"time":1.5667,"color":"ffffff00"}]},"eye_light3":{"color":[{"time":0.6667,"color":"ffffff00"},{"time":0.7,"color":"ffffffff","curve":"stepped"},{"time":1.4667,"color":"ffffffff"},{"time":1.5667,"color":"ffffff00"}]},"eye_light4":{"color":[{"time":0.6667,"color":"ffffff00"},{"time":0.7,"color":"ffffffff","curve":"stepped"},{"time":1.4667,"color":"ffffffff"},{"time":1.5667,"color":"ffffff00"}]},"face_01":{"color":[{"color":"ffffffff","curve":"stepped"},{"time":0.5667,"color":"ffffffff","curve":0.331,"c2":0.33,"c3":0.665,"c4":0.66},{"time":0.6,"color":"ffffff00","curve":"stepped"},{"time":1.5,"color":"ffffff00","curve":0.369,"c2":0.47,"c3":0.753},{"time":1.5667,"color":"ffffffff"}]},"face_effect":{"color":[{"time":0.5667,"color":"ffffff00"},{"time":0.7,"color":"ffffffff","curve":"stepped"},{"time":1.4,"color":"ffffffff"},{"time":1.5667,"color":"ffffff00"}]},"head":{"color":[{"color":"ffffff00"}]},"head2":{"color":[{"color":"ffffffff"}]},"head_02":{"color":[{"color":"ffffff00"}]},"head_02-2":{"color":[{"color":"ffffffff"}]},"head_03":{"color":[{"color":"ffffff00"}]},"head_shadow-2":{"color":[{"color":"ffffffff"}]}},"bones":{"body_01":{"translate":[{"curve":0.25,"c3":0.75},{"time":0.3333,"y":-5.21},{"time":0.6,"y":4.23},{"time":0.8333}]},"body_02":{"rotate":[{"curve":0.245,"c3":0.638,"c4":0.56},{"time":0.8667,"angle":2.4,"curve":0.382,"c2":0.55,"c3":0.742},{"time":1.5667}],"translate":[{"curve":0.25,"c3":0.75},{"time":0.3333,"x":-9.03,"y":-0.24},{"time":0.6,"x":0.45,"y":0.01},{"time":0.8333,"x":-7.16,"y":-0.19},{"time":1.1}]},"nack":{"translate":[{"curve":0.25,"c3":0.75},{"time":0.3333,"x":-1.27,"y":0.05},{"time":0.6,"x":1.05,"y":-0.04},{"time":0.8333}]},"head":{"rotate":[{"time":0.6,"curve":0.328,"c2":0.31,"c3":0.661,"c4":0.64},{"time":0.8667,"angle":12.6,"curve":0.324,"c2":0.29,"c3":0.657,"c4":0.63},{"time":1.3333,"angle":10.8,"curve":0.324,"c2":0.29,"c3":0.657,"c4":0.63},{"time":1.5667}],"translate":[{"curve":0.25,"c3":0.75},{"time":0.3333,"x":-1.59},{"time":0.6,"x":0.83},{"time":0.8667,"x":-3.02,"curve":"stepped"},{"time":1.3333,"x":-3.02,"curve":0.498,"c2":0.24,"c3":0.922,"c4":0.78},{"time":1.5667}]},"ear_R":{"rotate":[{"time":0.3667,"curve":0.334,"c2":0.33,"c3":0.668,"c4":0.67},{"time":0.4667,"angle":3,"curve":0.335,"c2":0.34,"c3":0.668,"c4":0.67},{"time":0.6667,"angle":-18.9,"curve":0.381,"c2":0.55,"c3":0.742},{"time":0.7333}],"translate":[{"x":-3.5,"y":-1.48}]},"ear_L":{"rotate":[{"time":0.3667,"curve":0.334,"c2":0.33,"c3":0.668,"c4":0.67},{"time":0.4667,"angle":-6,"curve":0.335,"c2":0.34,"c3":0.668,"c4":0.67},{"time":0.6667,"angle":15.3,"curve":0.381,"c2":0.55,"c3":0.742},{"time":0.7333}],"translate":[{"x":-1.5,"y":4.44}]},"galss":{"translate":[{"x":-3.81,"y":-0.77}]},"shoulder_L":{"rotate":[{"time":0.1333,"curve":0.25,"c3":0.75},{"time":0.6333,"angle":-17.19,"curve":"stepped"},{"time":1.2,"angle":-17.19,"curve":0.25,"c3":0.75},{"time":1.5667}],"translate":[{"time":0.1333,"curve":0.25,"c3":0.75},{"time":0.6333,"x":17.3,"y":-0.73,"curve":0.25,"c3":0.75},{"time":0.9333,"x":15.22,"y":-3.77,"curve":"stepped"},{"time":1.2,"x":15.22,"y":-3.77},{"time":1.5667}],"scale":[{"time":0.1333,"curve":0.25,"c3":0.75},{"time":0.6333,"x":0.815,"curve":0.25,"c3":0.75},{"time":1.5667}]},"arm_L":{"rotate":[{"time":0.1333,"curve":0.25,"c3":0.75},{"time":0.6333,"angle":162.02,"curve":0.25,"c3":0.75},{"time":0.9333,"angle":157.55,"curve":"stepped"},{"time":1.2,"angle":157.55},{"time":1.5667}],"translate":[{"time":0.1333,"curve":0.274,"c3":0.62,"c4":0.4},{"time":0.2667,"x":4.63,"y":0.2,"curve":0.336,"c2":0.34,"c3":0.758},{"time":0.6333,"x":-6.68,"y":-5.91,"curve":0.25,"c3":0.75},{"time":0.9333,"x":-3.38,"y":-4.64},{"time":1.2,"x":-6.18,"y":-5.77},{"time":1.4667,"x":2.45,"y":1.11},{"time":1.5667}],"scale":[{"time":0.1333,"curve":0.25,"c3":0.75},{"time":0.6333,"x":1.275,"curve":0.25,"c3":0.75},{"time":1.5667}]},"shoulder_R":{"rotate":[{"time":0.6},{"time":0.8333,"angle":0.3},{"time":1.5667}]},"arm_R":{"translate":[{"curve":0.247,"c3":0.631,"c4":0.53},{"time":0.3333,"x":-1.49,"y":0.14,"curve":0.379,"c2":0.53,"c3":0.746},{"time":0.6}]},"hand_L":{"rotate":[{"time":0.6333,"curve":0.25,"c3":0.75},{"time":0.9333,"angle":12.82,"curve":"stepped"},{"time":1.2,"angle":12.82},{"time":1.5667}],"translate":[{"time":0.1333,"curve":0.25,"c3":0.625,"c4":0.5},{"time":0.6333,"x":3.3,"y":-4.79,"curve":0.276,"c3":0.621,"c4":0.4},{"time":0.9333,"x":1.45,"y":-3.81},{"time":1.1667,"x":1.43,"y":-3.77},{"time":1.5667}]},"hand_L2":{"translate":[{"curve":0.25,"c3":0.625,"c4":0.5},{"time":0.3333,"y":-4.84},{"time":0.6,"y":3.7},{"time":0.8333,"y":-3.1},{"time":1.1}]},"hand_R":{"rotate":[{"curve":0.279,"c3":0.622,"c4":0.39},{"time":0.3333,"angle":10.2,"curve":0.316,"c2":0.27,"c3":0.654,"c4":0.63},{"time":0.6,"angle":14.06,"curve":0.331,"c2":0.33,"c3":0.669,"c4":0.67},{"time":0.8333,"angle":1.29,"curve":0.381,"c2":0.54,"c3":0.744},{"time":1.1}]},"hand_R2":{"translate":[{"curve":0.25,"c3":0.625,"c4":0.5},{"time":0.3333,"y":-11.45},{"time":0.6,"y":9.08},{"time":0.8333,"y":-3.1},{"time":1.1}]},"tail_01":{"rotate":[{"curve":0.25,"c3":0.625,"c4":0.5},{"time":0.4,"angle":4.05},{"time":0.6333,"angle":10.58},{"time":0.8333,"angle":-0.9},{"time":1.1333}]},"tail_02":{"rotate":[{"curve":0.25,"c3":0.625,"c4":0.5},{"time":0.3333,"angle":-3.49},{"time":0.5667,"angle":-2.32},{"time":0.7667,"angle":-11.72},{"time":1.0667}]},"tail_03":{"rotate":[{"curve":0.274,"c3":0.62,"c4":0.4},{"time":0.3667,"angle":20.82,"curve":0.359,"c2":0.44,"c3":0.698,"c4":0.8},{"time":0.7667,"angle":-25.27,"curve":0.362,"c2":0.64,"c3":0.698},{"time":1.0667,"angle":-14.4,"curve":0.315,"c2":0.27,"c3":0.677,"c4":0.7},{"time":1.5667}],"translate":[{"curve":0.274,"c3":0.62,"c4":0.4},{"time":0.3667,"x":-5.13,"y":2.32,"curve":0.359,"c2":0.44,"c3":0.698,"c4":0.8},{"time":0.7667,"x":5.99,"y":-10.25,"curve":0.362,"c2":0.64,"c3":0.698},{"time":1.0667,"x":3.93,"y":-1.95,"curve":0.315,"c2":0.27,"c3":0.677,"c4":0.7},{"time":1.5667}]},"hair_03":{"rotate":[{"time":0.3333},{"time":0.5667,"angle":7.5},{"time":0.8333,"angle":-12.9},{"time":1.0333}]},"hair_02":{"rotate":[{"time":0.3333},{"time":0.5667,"angle":-5.4},{"time":0.8333,"angle":17.1},{"time":1.0333}]},"hair_01":{"rotate":[{"time":0.3333},{"time":0.5667,"angle":-8.4},{"time":0.8333,"angle":14.1},{"time":1.0333}]},"hair_04":{"rotate":[{"time":0.3333},{"time":0.5667,"angle":19.5},{"time":0.8333,"angle":-11.1},{"time":1.0333}]},"hair_05":{"rotate":[{"time":0.3333},{"time":0.5667,"angle":-13.5},{"time":0.8333,"angle":16.5},{"time":1.0333}]},"box_01-R":{"rotate":[{},{"time":0.3333,"angle":2.7},{"time":0.6,"angle":-2.7},{"time":0.8333}],"translate":[{},{"time":0.3333,"y":-3.85},{"time":0.6,"y":5.49},{"time":0.8333}]},"box_02":{"rotate":[{"time":0.2333},{"time":0.4667,"angle":-16.8},{"time":0.7,"angle":33.3},{"time":0.9,"angle":-5.83},{"time":1.1333}]},"box_01-L":{"rotate":[{},{"time":0.3333,"angle":4.5},{"time":0.6}],"translate":[{},{"time":0.3333,"y":-2.59},{"time":0.6,"y":3.86},{"time":0.8333}]},"book":{"scale":[{},{"time":0.3667,"y":0.905},{"time":0.5667,"y":1.05},{"time":0.7667,"y":0.905},{"time":0.9333}]},"eye_light":{"translate":[{"x":-7.23,"y":2.21}],"scale":[{"time":0.7667},{"time":0.9,"x":1.335,"y":1.245},{"time":1.1},{"time":1.2,"x":1.335,"y":1.245},{"time":1.3667}]},"eye_light2":{"translate":[{"x":-5.68,"y":2.12}],"scale":[{"time":0.7667},{"time":0.9,"x":1.335,"y":1.245},{"time":1.1},{"time":1.2,"x":1.335,"y":1.245},{"time":1.3667}]},"book_01":{"translate":[{},{"time":0.3667,"y":-3.62},{"time":0.5667,"x":1.21,"y":3.22},{"time":0.7667,"x":-0.4,"y":-4.02},{"time":0.9333}]},"box_05":{"rotate":[{"time":0.2333},{"time":0.5,"angle":10.5},{"time":0.7,"angle":-13.5},{"time":0.9,"angle":4.2},{"time":1.0667}],"translate":[{"time":0.5},{"time":0.7,"x":0.55},{"time":0.9}]},"book_05":{"translate":[{"time":0.4333},{"time":0.6333,"y":5.32},{"time":0.8333,"y":-2.67},{"time":1,"y":5.23},{"time":1.2}]},"book_06":{"translate":[{"time":0.4333},{"time":0.6333,"y":6.43},{"time":0.8333,"y":-1.33},{"time":1,"y":2.01},{"time":1.1333,"y":3.22},{"time":1.3333}]},"book_04":{"translate":[{"time":0.4333},{"time":0.6333,"y":5.86},{"time":0.8333,"y":-5.13},{"time":1,"y":2.81},{"time":1.2}]},"Center":{"translate":[{"curve":0.258,"c3":0.619,"c4":0.45},{"time":0.3333,"y":-2.76,"curve":0.334,"c2":0.34,"c3":0.683,"c4":0.72},{"time":0.6,"y":2.99,"curve":0.381,"c2":0.59,"c3":0.728},{"time":0.8333}],"scale":[{"curve":0.258,"c3":0.619,"c4":0.45},{"time":0.3333,"y":0.975,"curve":0.334,"c2":0.34,"c3":0.683,"c4":0.72},{"time":0.6,"y":1.005,"curve":0.381,"c2":0.59,"c3":0.728},{"time":0.8333}]},"book_02":{"scale":[{},{"time":0.3667,"y":0.905},{"time":0.5667,"y":1.05},{"time":0.7667,"y":0.905},{"time":0.9333}]}},"drawOrder":[{"time":0.3667,"offsets":[{"slot":"arm_L_01","offset":7},{"slot":"hand_L","offset":-28}]},{"time":1.5}]},"Greeting":{"slots":{"ear_L":{"color":[{"color":"ffffff00"}]},"ear_L-2":{"color":[{"color":"ffffffff"}]},"ear_R":{"color":[{"color":"ffffff00"}]},"ear_R-2":{"color":[{"color":"ffffffff"}]},"eye2_01":{"color":[{"time":0.5,"color":"ffffff00"},{"time":0.5667,"color":"ffffffff","curve":"stepped"},{"time":1.7333,"color":"ffffffff"},{"time":1.7667,"color":"ffffff00"}]},"eye2_02":{"color":[{"time":1.5667,"color":"ffffff00"},{"time":1.6,"color":"ffffffff","curve":"stepped"},{"time":1.7,"color":"ffffffff"},{"time":1.7333,"color":"ffffff00"}]},"face-02":{"color":[{"time":0.5,"color":"ffffff00","curve":0.25,"c3":0.75},{"time":0.5667,"color":"ffffffff","curve":"stepped"},{"time":1.7333,"color":"ffffffff","curve":0.25,"c3":0.75},{"time":1.7667,"color":"ffffff00"}]},"face_01":{"color":[{"color":"ffffffff"}]},"head":{"color":[{"color":"ffffff00"}]},"head2":{"color":[{"color":"ffffffff"}]},"head_02":{"color":[{"color":"ffffff00"}]},"head_02-2":{"color":[{"color":"ffffffff"}]},"head_03":{"color":[{"color":"ffffff00"}]},"head_shadow-2":{"color":[{"color":"ffffffff"}]},"sparkle":{"color":[{"time":0.9667,"color":"ffffff00"},{"time":1,"color":"ffffffff"}]}},"bones":{"Center":{"translate":[{"curve":0.25,"c3":0.625,"c4":0.5},{"time":1,"y":-1.62,"curve":0.375,"c2":0.5,"c3":0.75},{"time":2}]},"body_01":{"translate":[{"curve":0.242,"c3":0.664,"c4":0.66},{"time":0.4667,"y":-1.13,"curve":0.38,"c2":0.6,"c3":0.726},{"time":0.8667,"y":-1.42,"curve":"stepped"},{"time":1.5,"y":-1.42,"curve":0.25,"c3":0.75},{"time":2}]},"head":{"rotate":[{"curve":0.266,"c3":0.618,"c4":0.42},{"time":0.6333,"angle":6.9,"curve":0.266,"c3":0.618,"c4":0.42},{"time":0.9333,"angle":10.5,"curve":0.266,"c3":0.618,"c4":0.42},{"time":1.1,"angle":4.2,"curve":0.266,"c3":0.618,"c4":0.42},{"time":1.3333,"angle":6.9,"curve":"stepped"},{"time":1.5,"angle":6.9,"curve":0.266,"c3":0.618,"c4":0.42},{"time":2}],"translate":[{"curve":0.25,"c3":0.75},{"time":0.6333,"x":-3.47,"y":0.53,"curve":"stepped"},{"time":0.9333,"x":-3.47,"y":0.53,"curve":0.25,"c3":0.75},{"time":1.1,"x":-0.71,"y":-0.18,"curve":0.25,"c3":0.75},{"time":1.3333,"x":-2.81,"curve":"stepped"},{"time":1.5,"x":-2.81,"curve":0.25,"c3":0.75},{"time":1.7}]},"nack":{"rotate":[{"curve":0.25,"c3":0.75},{"time":0.6333,"angle":4.8,"curve":"stepped"},{"time":1.5,"angle":4.8,"curve":0.25,"c3":0.75},{"time":2}]},"hand_L":{"translate":[{"curve":0.25,"c3":0.625,"c4":0.5},{"time":0.6333,"x":15.63,"y":-0.65,"curve":"stepped"},{"time":0.9333,"x":15.63,"y":-0.65,"curve":0.25,"c3":0.625,"c4":0.5},{"time":1.1,"x":16.37,"y":-0.47,"curve":0.25,"c3":0.625,"c4":0.5},{"time":1.3333,"x":15.63,"y":-0.65,"curve":"stepped"},{"time":1.5,"x":15.63,"y":-0.65,"curve":0.25,"c3":0.625,"c4":0.5},{"time":2}]},"box_05":{"rotate":[{},{"time":1,"angle":3.9},{"time":2}]},"body_02":{"rotate":[{"time":0.6,"curve":0.37,"c2":0.63,"c3":0.708},{"time":0.9333,"angle":-0.02,"curve":0.276,"c3":0.621,"c4":0.4},{"time":1.1,"angle":-1.42,"curve":0.318,"c2":0.28,"c3":0.656,"c4":0.63},{"time":1.3333,"angle":-0.02,"curve":"stepped"},{"time":1.5,"angle":-0.02,"curve":0.25,"c3":0.75},{"time":2}],"translate":[{"curve":0.243,"c3":0.692,"c4":0.76},{"time":0.6,"x":-2.77,"y":-0.07,"curve":0.37,"c2":0.63,"c3":0.708},{"time":0.9333,"x":-3.04,"y":-0.08,"curve":"stepped"},{"time":1.5,"x":-3.04,"y":-0.08,"curve":0.25,"c3":0.75},{"time":2}]},"box_02":{"rotate":[{},{"time":1,"angle":-4.35},{"time":2}]},"hair_03":{"rotate":[{"time":0.9},{"time":1.1,"angle":7.2},{"time":1.2667,"angle":-13.41},{"time":1.5,"angle":7.2},{"time":1.7}]},"shoulder_R":{"translate":[{"curve":0.25,"c3":0.75},{"time":0.6333,"x":1.9,"y":-0.08,"curve":"stepped"},{"time":1.5,"x":1.9,"y":-0.08,"curve":0.25,"c3":0.75},{"time":2}]},"galss":{"translate":[{"x":3.92,"y":-3.9},{"time":0.6333,"x":1.87,"y":-4.24,"curve":"stepped"},{"time":0.9333,"x":1.87,"y":-4.24},{"time":1.1,"x":8.67,"y":-4.15},{"time":1.3333,"x":3.92,"y":-3.9}]},"ear_L":{"rotate":[{"time":1.0333,"curve":0.334,"c2":0.33,"c3":0.668,"c4":0.67},{"time":1.1333,"angle":21.3,"curve":0.335,"c2":0.34,"c3":0.668,"c4":0.67},{"time":1.2,"angle":-10.5,"curve":0.381,"c2":0.55,"c3":0.742},{"time":1.3667}],"translate":[{"x":-1.5,"y":4.44}]},"hand_R":{"translate":[{"curve":0.25,"c3":0.625,"c4":0.5},{"time":0.6333,"x":1.97,"y":1.52,"curve":"stepped"},{"time":0.9333,"x":1.97,"y":1.52,"curve":0.309,"c2":0.24,"c3":0.646,"c4":0.58},{"time":1.1,"x":1.14,"y":2.15,"curve":0.32,"c2":0.29,"c3":0.66,"c4":0.65},{"time":1.3333,"x":1.97,"y":1.52,"curve":"stepped"},{"time":1.5,"x":1.97,"y":1.52,"curve":0.25,"c3":0.625,"c4":0.5},{"time":2}]},"hand_R2":{"translate":[{"curve":0.25,"c3":0.625,"c4":0.5},{"time":0.6333,"y":-4.15,"curve":"stepped"},{"time":1.5,"y":-4.15,"curve":0.25,"c3":0.625,"c4":0.5},{"time":2}]},"ear_R":{"rotate":[{"time":1.0333,"curve":0.334,"c2":0.33,"c3":0.668,"c4":0.67},{"time":1.1333,"angle":-15,"curve":0.335,"c2":0.34,"c3":0.668,"c4":0.67},{"time":1.2,"angle":4.8,"curve":0.381,"c2":0.55,"c3":0.742},{"time":1.3667}],"translate":[{"x":-3.5,"y":-1.48}]},"hair_04":{"rotate":[{"time":0.9},{"time":1.1,"angle":11.1},{"time":1.2667,"angle":-10.66},{"time":1.5,"angle":11.1},{"time":1.7}]},"hair_01":{"rotate":[{"time":0.9},{"time":1.1,"angle":-8.1},{"time":1.2667,"angle":10.58},{"time":1.5,"angle":-8.1},{"time":1.7}]},"hair_02":{"rotate":[{"time":0.9},{"time":1.1,"angle":-8.1},{"time":1.2667,"angle":20.47},{"time":1.5,"angle":-8.1},{"time":1.7}]},"hair_05":{"rotate":[{"time":0.9},{"time":1.1,"angle":-9.3},{"time":1.2667,"angle":19.01},{"time":1.5,"angle":-9.3},{"time":1.7}]},"tail_01":{"rotate":[{"curve":0.25,"c3":0.625,"c4":0.5},{"time":0.9,"angle":-6.4,"curve":0.337,"c2":0.35,"c3":0.674,"c4":0.69},{"time":1.2667,"angle":21.7,"curve":0.382,"c2":0.57,"c3":0.736},{"time":2}]},"tail_02":{"rotate":[{"curve":0.25,"c3":0.75},{"time":0.9,"angle":-3.26,"curve":0.266,"c3":0.618,"c4":0.42},{"time":1.2667,"angle":-4.88,"curve":0.349,"c2":0.39,"c3":0.757},{"time":2}]},"tail_03":{"rotate":[{"curve":0.274,"c3":0.62,"c4":0.4},{"time":0.5667,"angle":-14.4,"curve":0.319,"c2":0.29,"c3":0.657,"c4":0.63},{"time":1.1,"angle":-27.69,"curve":0.332,"c2":0.33,"c3":0.668,"c4":0.67},{"time":1.2667,"angle":19.26,"curve":0.34,"c2":0.35,"c3":0.676,"c4":0.7},{"time":1.5333,"angle":20.82,"curve":0.382,"c2":0.58,"c3":0.731},{"time":2}],"translate":[{"curve":0.274,"c3":0.62,"c4":0.4},{"time":0.5667,"x":3.93,"y":-1.95,"curve":0.32,"c2":0.29,"c3":0.657,"c4":0.63},{"time":1.1,"x":11.2,"y":-12.85,"curve":0.333,"c2":0.33,"c3":0.666,"c4":0.67},{"time":1.2667,"x":4.12,"y":6.36,"curve":0.34,"c2":0.35,"c3":0.676,"c4":0.7},{"time":1.5333,"x":-5.13,"y":2.32,"curve":0.382,"c2":0.58,"c3":0.731},{"time":2}]},"shoulder_L":{"rotate":[{"curve":0.25,"c3":0.75},{"time":0.6333,"angle":-17.19,"curve":"stepped"},{"time":0.9333,"angle":-17.19,"curve":0.25,"c3":0.75},{"time":1.1,"angle":-21.19,"curve":0.25,"c3":0.75},{"time":1.3333,"angle":-17.19,"curve":"stepped"},{"time":1.5,"angle":-17.19,"curve":0.25,"c3":0.75},{"time":2}],"translate":[{"curve":0.25,"c3":0.75},{"time":0.6333,"x":29.96,"y":-1.25,"curve":"stepped"},{"time":0.9333,"x":29.96,"y":-1.25,"curve":0.25,"c3":0.75},{"time":1.1,"x":27.73,"y":-3.95,"curve":0.25,"c3":0.75},{"time":1.3333,"x":31.37,"y":-1.31,"curve":"stepped"},{"time":1.5,"x":31.37,"y":-1.31,"curve":0.25,"c3":0.75},{"time":2}],"scale":[{"curve":0.25,"c3":0.75},{"time":0.6333,"x":0.815,"curve":"stepped"},{"time":1.5,"x":0.815,"curve":0.25,"c3":0.75},{"time":2}]},"arm_L":{"rotate":[{"curve":0.25,"c3":0.75},{"time":0.6333,"angle":162.02,"curve":0.25,"c3":0.75},{"time":0.9333,"angle":163.51,"curve":0.25,"c3":0.75},{"time":1.1,"angle":170.94,"curve":0.25,"c3":0.75},{"time":1.3333,"angle":162.02,"curve":"stepped"},{"time":1.5,"angle":162.02,"curve":0.258,"c3":0.619,"c4":0.45},{"time":1.7,"angle":74.91,"curve":0.363,"c2":0.44,"c3":0.755},{"time":2}],"translate":[{"curve":0.274,"c3":0.62,"c4":0.4},{"time":0.1667,"x":4.63,"y":0.2,"curve":0.336,"c2":0.34,"c3":0.758},{"time":0.6333,"x":-6.68,"y":-5.91,"curve":"stepped"},{"time":0.9333,"x":-6.68,"y":-5.91,"curve":0.25,"c3":0.75},{"time":1.1,"x":-9.02,"y":-7.13,"curve":0.25,"c3":0.75},{"time":1.3333,"x":-6.68,"y":-5.91,"curve":"stepped"},{"time":1.5,"x":-6.68,"y":-5.91,"curve":0.258,"c3":0.619,"c4":0.45},{"time":1.7,"x":0.86,"y":-1.97,"curve":0.363,"c2":0.44,"c3":0.755},{"time":1.8667,"x":4.63,"y":0.2,"curve":0.336,"c2":0.34,"c3":0.758},{"time":2}],"scale":[{"curve":0.25,"c3":0.75},{"time":0.6333,"x":1.275,"curve":"stepped"},{"time":1.5,"x":1.275,"curve":0.25,"c3":0.75},{"time":2}]},"sparkle":{"translate":[{"x":-2.75,"y":-84.09}],"scale":[{"x":0,"y":0,"curve":"stepped"},{"time":1,"x":0,"y":0},{"time":1.1667,"x":0.525,"y":0.635,"curve":"stepped"},{"time":1.2667,"x":0.525,"y":0.635},{"time":1.3667,"x":0,"y":0}]},"book":{"rotate":[{},{"time":0.6,"angle":1.01},{"time":1.3667,"angle":-0.6},{"time":2}],"scale":[{},{"time":0.9667,"x":0.989,"y":0.989,"curve":0.375,"c2":0.5,"c3":0.75},{"time":2}]},"book_01":{"rotate":[{},{"time":0.9667,"angle":-1.2},{"time":2}],"scale":[{},{"time":0.9667,"x":0.989,"y":0.989,"curve":0.375,"c2":0.5,"c3":0.75},{"time":2}]},"book_02":{"rotate":[{},{"time":0.4667,"angle":-0.5},{"time":1.4333,"angle":1.61},{"time":2}],"scale":[{},{"time":0.9667,"x":0.989,"y":0.989,"curve":0.375,"c2":0.5,"c3":0.75},{"time":2}]},"book_06":{"rotate":[{"angle":3.9,"curve":0.25,"c3":0.75},{"time":0.8333,"curve":0.25,"c3":0.75},{"time":1.6667,"angle":3.9}]},"book_05":{"rotate":[{"angle":1.73},{"time":0.4},{"time":1.2333,"angle":3.6},{"time":1.6667,"angle":1.73}]},"book_04":{"rotate":[{},{"time":0.8333,"angle":3.6},{"time":1.6667}]}},"drawOrder":[{"time":0.2,"offsets":[{"slot":"arm_L_01","offset":7}]},{"time":1.8667}]},"Idle":{"slots":{"eye_01":{"color":[{"time":0.8667,"color":"ffffff00","curve":"stepped"},{"time":0.9,"color":"ffffffff","curve":"stepped"},{"time":0.9333,"color":"ffffff00","curve":"stepped"},{"time":1.0333,"color":"ffffff00","curve":"stepped"},{"time":1.0667,"color":"ffffffff","curve":"stepped"},{"time":1.1,"color":"ffffff00"}]},"eye_02":{"color":[{"time":0.9,"color":"ffffff00","curve":"stepped"},{"time":0.9333,"color":"ffffffff","curve":"stepped"},{"time":1.0333,"color":"ffffffff","curve":"stepped"},{"time":1.0667,"color":"ffffff00"}]}},"bones":{"Center":{"scale":[{"curve":0.25,"c3":0.625,"c4":0.5},{"time":0.8333,"x":0.989,"y":0.989,"curve":0.375,"c2":0.5,"c3":0.75},{"time":1.6667}]},"body_01":{"translate":[{"curve":0.25,"c3":0.75},{"time":0.8333,"y":-1.91,"curve":0.25,"c3":0.75},{"time":1.6667}],"scale":[{"curve":0.25,"c3":0.625,"c4":0.5},{"time":0.8333,"x":0.974,"y":0.974,"curve":0.375,"c2":0.5,"c3":0.75},{"time":1.6667}]},"body_02":{"translate":[{"curve":0.25,"c3":0.75},{"time":0.8333,"x":-2.71,"y":-0.07,"curve":0.25,"c3":0.75},{"time":1.6667}]},"head":{"rotate":[{"curve":0.25,"c3":0.75},{"time":0.5333,"angle":2.52,"curve":0.25,"c3":0.75},{"time":1.2,"angle":-3.44,"curve":0.25,"c3":0.75},{"time":1.6667}],"translate":[{"curve":0.25,"c3":0.75},{"time":0.8333,"x":-1.55,"curve":0.25,"c3":0.75},{"time":1.6667}],"shear":[{},{"time":0.8667,"x":3},{"time":1.6667}]},"ear_R":{"rotate":[{"time":0.8333,"curve":0.334,"c2":0.33,"c3":0.668,"c4":0.67},{"time":0.9333,"angle":-15,"curve":0.335,"c2":0.34,"c3":0.668,"c4":0.67},{"time":1,"angle":4.8,"curve":0.381,"c2":0.55,"c3":0.742},{"time":1.1}]},"ear_L":{"rotate":[{"time":0.8333,"curve":0.334,"c2":0.33,"c3":0.668,"c4":0.67},{"time":0.9333,"angle":21.3,"curve":0.335,"c2":0.34,"c3":0.668,"c4":0.67},{"time":1,"angle":-10.5,"curve":0.381,"c2":0.55,"c3":0.742},{"time":1.1}]},"shoulder_L":{"translate":[{"curve":0.25,"c3":0.75},{"time":0.8333,"x":2.9,"y":-0.12,"curve":0.25,"c3":0.75},{"time":1.6667}]},"shoulder_R":{"translate":[{"curve":0.25,"c3":0.75},{"time":0.8333,"x":3.55,"y":-0.15,"curve":0.25,"c3":0.75},{"time":1.6667}]},"hand_L":{"translate":[{"curve":0.25,"c3":0.625,"c4":0.5},{"time":0.8333,"x":0.76,"y":-0.22,"curve":0.375,"c2":0.5,"c3":0.75},{"time":1.6667}]},"hand_L2":{"translate":[{"curve":0.25,"c3":0.625,"c4":0.5},{"time":0.8333,"y":-1.68,"curve":0.375,"c2":0.5,"c3":0.75},{"time":1.6667}]},"hand_R":{"translate":[{"curve":0.25,"c3":0.625,"c4":0.5},{"time":0.8333,"x":0.08,"y":0.06,"curve":0.375,"c2":0.5,"c3":0.75},{"time":1.6667}]},"hand_R2":{"translate":[{"curve":0.25,"c3":0.625,"c4":0.5},{"time":0.8333,"y":-1.68,"curve":0.375,"c2":0.5,"c3":0.75},{"time":1.6667}]},"tail_01":{"rotate":[{"curve":0.25,"c3":0.625,"c4":0.5},{"time":0.8333,"angle":-1.3,"curve":0.375,"c2":0.5,"c3":0.75},{"time":1.6667}]},"tail_02":{"rotate":[{"curve":0.25,"c3":0.625,"c4":0.5},{"time":0.8333,"angle":-16.16,"curve":0.375,"c2":0.5,"c3":0.75},{"time":1.6667}]},"tail_03":{"rotate":[{"curve":0.274,"c3":0.62,"c4":0.4},{"time":0.4333,"angle":-14.4,"curve":0.315,"c2":0.27,"c3":0.677,"c4":0.7},{"time":1.1667,"angle":20.82,"curve":0.382,"c2":0.58,"c3":0.731},{"time":1.6667}],"translate":[{"curve":0.274,"c3":0.62,"c4":0.4},{"time":0.4333,"x":3.93,"y":-1.95,"curve":0.315,"c2":0.27,"c3":0.677,"c4":0.7},{"time":1.1667,"x":-5.13,"y":2.32,"curve":0.382,"c2":0.58,"c3":0.731},{"time":1.6667}]},"hair_03":{"rotate":[{"curve":0.25,"c3":0.75},{"time":0.8333,"angle":4.8,"curve":0.25,"c3":0.75},{"time":1.6667}]},"hair_02":{"rotate":[{"curve":0.25,"c3":0.75},{"time":0.8333,"angle":-6.6,"curve":0.25,"c3":0.75},{"time":1.6667}]},"hair_01":{"rotate":[{"curve":0.25,"c3":0.75},{"time":0.8333,"angle":-4.5,"curve":0.25,"c3":0.75},{"time":1.6667}]},"hair_04":{"rotate":[{"curve":0.25,"c3":0.75},{"time":0.8333,"angle":-5.1,"curve":0.25,"c3":0.75},{"time":1.6667}]},"hair_05":{"rotate":[{"curve":0.25,"c3":0.75},{"time":0.8333,"angle":5.1,"curve":0.25,"c3":0.75},{"time":1.6667}]},"box_02":{"rotate":[{},{"time":0.8333,"angle":-8.7},{"time":1.6667}]},"box_05":{"rotate":[{},{"time":0.8333,"angle":7.8},{"time":1.6667}]},"book":{"rotate":[{},{"time":0.5333,"angle":1.01},{"time":1.1667,"angle":-0.6},{"time":1.6667}],"scale":[{},{"time":0.8333,"x":0.989,"y":0.989,"curve":0.375,"c2":0.5,"c3":0.75},{"time":1.6667}]},"book_02":{"rotate":[{},{"time":0.4,"angle":-0.5},{"time":1.2333,"angle":1.61},{"time":1.6667}],"scale":[{},{"time":0.8333,"x":0.989,"y":0.989,"curve":0.375,"c2":0.5,"c3":0.75},{"time":1.6667}]},"book_06":{"rotate":[{"angle":3.9,"curve":0.25,"c3":0.75},{"time":0.8333,"curve":0.25,"c3":0.75},{"time":1.6667,"angle":3.9}]},"book_05":{"rotate":[{"angle":1.73},{"time":0.4},{"time":1.2333,"angle":3.6},{"time":1.6667,"angle":1.73}]},"book_04":{"rotate":[{},{"time":0.8333,"angle":3.6},{"time":1.6667}]}},"drawOrder":[{"offsets":[{"slot":"arm_R_01","offset":1}]}]},"Touch":{"slots":{"eye_01":{"color":[{"time":0.4667,"color":"ffffff00","curve":"stepped"},{"time":0.5,"color":"ffffffff","curve":"stepped"},{"time":0.5333,"color":"ffffff00","curve":"stepped"},{"time":0.6333,"color":"ffffff00","curve":"stepped"},{"time":0.6667,"color":"ffffffff","curve":"stepped"},{"time":0.7,"color":"ffffff00"}]},"eye_02":{"color":[{"time":0.5,"color":"ffffff00","curve":"stepped"},{"time":0.5333,"color":"ffffffff","curve":"stepped"},{"time":0.6333,"color":"ffffffff","curve":"stepped"},{"time":0.6667,"color":"ffffff00"}]}},"bones":{"body_01":{"translate":[{},{"time":0.2667,"y":-5.21},{"time":0.5667,"y":4.23},{"time":0.8}]},"body_02":{"rotate":[{"time":0.5667},{"time":0.8,"angle":3.3},{"time":1.2,"angle":0.48},{"time":1.5}],"translate":[{},{"time":0.2667,"x":-2.58,"y":-0.07},{"time":0.5667,"x":1.11,"y":0.03},{"time":0.8}]},"nack":{"rotate":[{"time":0.2667},{"time":0.5667,"angle":-2.1},{"time":0.8,"angle":3},{"time":1.1333,"angle":2.61},{"time":1.5}],"translate":[{},{"time":0.2667,"x":-1.27,"y":0.05},{"time":0.5667,"x":1.05,"y":-0.04},{"time":0.8}]},"head":{"rotate":[{},{"time":0.2667,"angle":-1.56},{"time":0.5667,"angle":-3.3},{"time":0.8667,"angle":9.3,"curve":0.25,"c3":0.75},{"time":1.1667,"angle":6.23,"curve":0.25,"c3":0.75},{"time":1.5}],"translate":[{},{"time":0.2667,"x":-1.59},{"time":0.5667,"x":0.83},{"time":0.8667}],"shear":[{"time":0.5667},{"time":0.8667,"x":3.3,"curve":"stepped"},{"time":1.1667,"x":3.3},{"time":1.5}]},"ear_R":{"rotate":[{"time":0.6,"curve":0.334,"c2":0.33,"c3":0.668,"c4":0.67},{"time":0.7,"angle":3,"curve":0.335,"c2":0.34,"c3":0.668,"c4":0.67},{"time":0.8,"angle":-18.9,"curve":0.381,"c2":0.55,"c3":0.742},{"time":0.9}]},"ear_L":{"rotate":[{"time":0.6,"curve":0.334,"c2":0.33,"c3":0.668,"c4":0.67},{"time":0.7,"angle":-6,"curve":0.335,"c2":0.34,"c3":0.668,"c4":0.67},{"time":0.8,"angle":15.3,"curve":0.381,"c2":0.55,"c3":0.742},{"time":0.9}]},"shoulder_L":{"rotate":[{"time":0.5667},{"time":0.8,"angle":-1.2},{"time":1.5}]},"shoulder_R":{"rotate":[{"time":0.5667},{"time":0.8,"angle":0.3},{"time":1.5}]},"hand_L2":{"translate":[{},{"time":0.2667,"y":-6.99},{"time":0.5667,"y":4.71},{"time":0.8}]},"hand_R2":{"translate":[{},{"time":0.2667,"y":-6.03},{"time":0.5667,"y":7.26},{"time":0.8}]},"tail_01":{"rotate":[{},{"time":0.3333,"angle":4.05},{"time":0.6,"angle":10.58},{"time":0.8,"angle":-0.9},{"time":1.0667}]},"tail_02":{"rotate":[{},{"time":0.3333,"angle":-3.49},{"time":0.6,"angle":-2.32},{"time":0.8,"angle":-11.72},{"time":1.0667}]},"tail_03":{"rotate":[{"curve":0.274,"c3":0.62,"c4":0.4},{"time":0.4,"angle":20.82,"curve":0.382,"c2":0.58,"c3":0.731},{"time":1.1,"angle":-14.4,"curve":0.315,"c2":0.27,"c3":0.677,"c4":0.7},{"time":1.5}],"translate":[{"curve":0.274,"c3":0.62,"c4":0.4},{"time":0.4,"x":-5.13,"y":2.32,"curve":0.382,"c2":0.58,"c3":0.731},{"time":1.1,"x":3.93,"y":-1.95,"curve":0.315,"c2":0.27,"c3":0.677,"c4":0.7},{"time":1.5}]},"hair_03":{"rotate":[{"time":0.2667},{"time":0.5333,"angle":7.5},{"time":0.8,"angle":-12.9},{"time":1.0333}]},"hair_02":{"rotate":[{"time":0.2667},{"time":0.5333,"angle":-5.4},{"time":0.8,"angle":17.1},{"time":1.0333}]},"hair_01":{"rotate":[{"time":0.2667},{"time":0.5333,"angle":-8.4},{"time":0.8,"angle":14.1},{"time":1.0333}]},"hair_04":{"rotate":[{"time":0.2667},{"time":0.5333,"angle":19.5},{"time":0.8,"angle":-11.1},{"time":1.0333}]},"hair_05":{"rotate":[{"time":0.2667},{"time":0.5333,"angle":-13.5},{"time":0.8,"angle":16.5},{"time":1.0333}]},"box_02":{"rotate":[{"time":0.2333},{"time":0.4333,"angle":-16.8},{"time":0.7,"angle":33.3},{"time":0.9,"angle":-5.83},{"time":1.1333}]},"box_05":{"rotate":[{"time":0.2333},{"time":0.4333,"angle":10.5},{"time":0.7,"angle":-13.5},{"time":0.9,"angle":4.2},{"time":1.0667}],"translate":[{"time":0.4333},{"time":0.7,"x":0.55},{"time":0.9}]},"box_01-R":{"rotate":[{},{"time":0.2667,"angle":2.7},{"time":0.5667,"angle":-2.7},{"time":0.8}],"translate":[{},{"time":0.2667,"y":-3.85},{"time":0.5667,"y":5.49},{"time":0.8}]},"box_01-L":{"rotate":[{},{"time":0.2667,"angle":4.5},{"time":0.5667}],"translate":[{},{"time":0.2667,"y":-2.59},{"time":0.5667,"y":3.86},{"time":0.8}]},"book_06":{"translate":[{"time":0.3667},{"time":0.6,"y":6.43},{"time":0.8,"y":-1.33},{"time":0.9667,"y":2.01},{"time":1.1,"y":3.22},{"time":1.2333}]},"book_05":{"translate":[{"time":0.3667},{"time":0.6,"y":5.32},{"time":0.8,"y":-2.67},{"time":0.9667,"y":5.23},{"time":1.2}]},"book_04":{"translate":[{"time":0.3667},{"time":0.6,"y":5.86},{"time":0.8,"y":-5.13},{"time":0.9667,"y":2.81},{"time":1.2}]},"book":{"scale":[{},{"time":0.4667,"y":0.905},{"time":0.6667,"y":1.05},{"time":0.8667,"y":0.905},{"time":1.0667}]},"book_01":{"translate":[{},{"time":0.4,"y":-3.62},{"time":0.6,"x":1.21,"y":3.22},{"time":0.8,"x":-0.4,"y":-4.02},{"time":0.9667}]},"Center":{"translate":[{"curve":0.258,"c3":0.619,"c4":0.45},{"time":0.3667,"y":-2.76,"curve":0.334,"c2":0.34,"c3":0.683,"c4":0.72},{"time":0.6333,"y":2.99,"curve":0.381,"c2":0.59,"c3":0.728},{"time":0.8667}],"scale":[{"curve":0.258,"c3":0.619,"c4":0.45},{"time":0.3667,"y":0.975,"curve":0.334,"c2":0.34,"c3":0.683,"c4":0.72},{"time":0.6333,"y":1.005,"curve":0.381,"c2":0.59,"c3":0.728},{"time":0.8667}]},"book_02":{"scale":[{},{"time":0.4,"y":0.905},{"time":0.6,"y":1.05},{"time":0.8,"y":0.905},{"time":0.9667}]}}}}}